[
 {
  "nameEn": "Dancing Mad (Distant Worlds)",
  "types": [
   "Achievement"
  ],
  "category": "Raids II"
 },
 {
  "nameEn": "Carrots of Brilliance",
  "types": [
   "Cosmic Exploration"
  ],
  "category": "Others"
 },
 {
  "nameEn": "Landscaping",
  "types": [
   "Cosmic Exploration"
  ],
  "category": "Others"
 },
 {
  "nameEn": "Give It All (Orchestral Version)",
  "types": [
   "Premium"
  ],
  "category": "Online Store & Bonuses"
 },
 {
  "nameEn": "Windswept Echoes (Orchestral Version)",
  "types": [
   "Premium"
  ],
  "category": "Online Store & Bonuses"
 },
 {
  "nameEn": "Tomorrow and Tomorrow (Orchestral Version)",
  "types": [
   "Premium"
  ],
  "category": "Online Store & Bonuses"
 },
 {
  "nameEn": "Songs of Salt and Suffering (Orchestral Version)",
  "types": [
   "Premium"
  ],
  "category": "Online Store & Bonuses"
 },
 {
  "nameEn": "Triumph (Orchestral Version)",
  "types": [
   "Premium"
  ],
  "category": "Online Store & Bonuses"
 },
 {
  "nameEn": "The Nautilus Knoweth (Pulse 2)",
  "types": [
   "Premium"
  ],
  "category": "Online Store & Bonuses"
 },
 {
  "nameEn": "Athena, the Tireless One (Pulse 2)",
  "types": [
   "Premium"
  ],
  "category": "Online Store & Bonuses"
 },
 {
  "nameEn": "Fiend (Pulse 2)",
  "types": [
   "Premium"
  ],
  "category": "Online Store & Bonuses"
 },
 {
  "nameEn": "To the Edge (Pulse 2)",
  "types": [
   "Premium"
  ],
  "category": "Online Store & Bonuses"
 },
 {
  "nameEn": "Return to Oblivion (Pulse 2)",
  "types": [
   "Premium"
  ],
  "category": "Online Store & Bonuses"
 },
 {
  "nameEn": "The Republic of Bastok",
  "types": [
   "Raid"
  ],
  "category": "Raids II"
 },
 {
  "nameEn": "The Kingdom of San d'Oria",
  "types": [
   "Raid"
  ],
  "category": "Raids II"
 },
 {
  "nameEn": "Airship",
  "types": [
   "Raid"
  ],
  "category": "Raids II"
 },
 {
  "nameEn": "Recollection",
  "types": [
   "Raid"
  ],
  "category": "Raids II"
 },
 {
  "nameEn": "Anxiety",
  "types": [
   "Raid"
  ],
  "category": "Raids II"
 },
 {
  "nameEn": "Celestial Thunder",
  "types": [
   "Raid"
  ],
  "category": "Raids II"
 },
 {
  "nameEn": "Main Theme from FINAL FANTASY XI",
  "types": [
   "Quest"
  ],
  "category": "Raids II"
 },
 {
  "nameEn": "One Last Time",
  "types": [
   "Quest"
  ],
  "category": "Raids II"
 },
 {
  "nameEn": "Happily Ever After",
  "types": [
   "Quest"
  ],
  "category": "Raids II"
 },
 {
  "nameEn": "Fifth Ode: A Time for Prayer",
  "types": [
   "Quest"
  ],
  "category": "Raids II"
 },
 {
  "nameEn": "Second Ode: Distant Promises",
  "types": [
   "Raid"
  ],
  "category": "Raids II"
 },
 {
  "nameEn": "The Wyrm Who Would Be King",
  "types": [
   "Raid"
  ],
  "category": "Raids II"
 },
 {
  "nameEn": "Shinryu",
  "types": [
   "Raid"
  ],
  "category": "Raids II"
 },
 {
  "nameEn": "A Realm of Emptiness",
  "types": [
   "Raid"
  ],
  "category": "Raids II"
 },
 {
  "nameEn": "Ragnarok",
  "types": [
   "Raid"
  ],
  "category": "Raids II"
 },
 {
  "nameEn": "Forbidden Seal",
  "types": [
   "Raid"
  ],
  "category": "Raids II"
 },
 {
  "nameEn": "Vana'diel March #4",
  "types": [
   "Raid"
  ],
  "category": "Raids II"
 },
 {
  "nameEn": "Fated Strife -Besieged-",
  "types": [
   "Raid"
  ],
  "category": "Raids II"
 },
 {
  "nameEn": "Bustle of the Capital",
  "types": [
   "Raid"
  ],
  "category": "Raids II"
 },
 {
  "nameEn": "Feast of the Ladies",
  "types": [
   "Raid"
  ],
  "category": "Raids II"
 },
 {
  "nameEn": "The Federation of Windurst",
  "types": [
   "Raid"
  ],
  "category": "Raids II"
 },
 {
  "nameEn": "Fond Farewells",
  "types": [
   "Voyages"
  ],
  "category": "Quests"
 },
 {
  "nameEn": "For Hope and Happiness",
  "types": [
   "Treasure Hunt"
  ],
  "category": "Quests"
 },
 {
  "nameEn": "FINAL FANTASY V: The Final Battle (Dawntrail)",
  "types": [
   "Trial"
  ],
  "category": "Trials"
 },
 {
  "nameEn": "Untested Voyager",
  "types": [
   "Dungeon"
  ],
  "category": "Dungeons II"
 },
 {
  "nameEn": "Serenity Unending: A Bygone Medley (Orchestral Version)",
  "types": [
   "Premium"
  ],
  "category": "Online Store & Bonuses"
 },
 {
  "nameEn": "Smile (Orchestral Version)",
  "types": [
   "Premium"
  ],
  "category": "Online Store & Bonuses"
 },
 {
  "nameEn": "What Moves the Heart",
  "types": [
   "V&C Dungeon"
  ],
  "category": "Dungeons II"
 },
 {
  "nameEn": "Worthy Pursuits",
  "types": [
   "V&C Dungeon"
  ],
  "category": "Dungeons II"
 },
 {
  "nameEn": "Good King Moggle Mog XII (Pulse 2)",
  "types": [
   "Premium"
  ],
  "category": "Online Store & Bonuses"
 },
 {
  "nameEn": "Bee My Honey (Pulse 2)",
  "types": [
   "Premium"
  ],
  "category": "Online Store & Bonuses"
 },
 {
  "nameEn": "Dedicated to Moonlight (Pulse 2)",
  "types": [
   "Premium"
  ],
  "category": "Online Store & Bonuses"
 },
 {
  "nameEn": "Close in the Distance (Pulse 2)",
  "types": [
   "Premium"
  ],
  "category": "Online Store & Bonuses"
 },
 {
  "nameEn": "Windswept Echoes (Pulse 2)",
  "types": [
   "Premium"
  ],
  "category": "Online Store & Bonuses"
 },
 {
  "nameEn": "Metal - Brute Justice Mode (The Primals)",
  "types": [
   "Premium"
  ],
  "category": "Online Store & Bonuses"
 },
 {
  "nameEn": "Locus (The Primals)",
  "types": [
   "Premium"
  ],
  "category": "Online Store & Bonuses"
 },
 {
  "nameEn": "Fiend (The Primals)",
  "types": [
   "Premium"
  ],
  "category": "Online Store & Bonuses"
 },
 {
  "nameEn": "Through the Maelstrom (The Primals)",
  "types": [
   "Premium"
  ],
  "category": "Online Store & Bonuses"
 },
 {
  "nameEn": "Under the Weight (The Primals)",
  "types": [
   "Premium"
  ],
  "category": "Online Store & Bonuses"
 },
 {
  "nameEn": "The Uncharted Road",
  "types": [
   "Cosmic Exploration"
  ],
  "category": "Others"
 },
 {
  "nameEn": "A Heartfelt Finish",
  "types": [
   "Event"
  ],
  "category": "Seasonal"
 },
 {
  "nameEn": "Flavors of the Heart",
  "types": [
   "Event"
  ],
  "category": "Seasonal"
 },
 {
  "nameEn": "Affection Confections",
  "types": [
   "Event"
  ],
  "category": "Seasonal"
 },
 {
  "nameEn": "Sweet Dreamer's Melody",
  "types": [
   "Event"
  ],
  "category": "Seasonal"
 },
 {
  "nameEn": "Jeuno (Starlight Celebration)",
  "types": [
   "Raid"
  ],
  "category": "Raids II"
 },
 {
  "nameEn": "The Ring's Reprieve",
  "types": [
   "Quest"
  ],
  "category": "Raids II"
 },
 {
  "nameEn": "The Arcadion",
  "types": [
   "Raid"
  ],
  "category": "Raids II"
 },
 {
  "nameEn": "Everything Burns",
  "types": [
   "Raid"
  ],
  "category": "Raids II"
 },
 {
  "nameEn": "Absolute Tyranny",
  "types": [
   "Raid"
  ],
  "category": "Raids II"
 },
 {
  "nameEn": "The Mirror",
  "types": [
   "Raid"
  ],
  "category": "Raids II"
 },
 {
  "nameEn": "Sinister",
  "types": [
   "Raid"
  ],
  "category": "Raids II"
 },
 {
  "nameEn": "Coming to Know You",
  "types": [
   "Achievement"
  ],
  "category": "Quests"
 },
 {
  "nameEn": "Mind Unclouded",
  "types": [
   "Achievement"
  ],
  "category": "Quests"
 },
 {
  "nameEn": "Blade Unbroken",
  "types": [
   "Treasure Hunt"
  ],
  "category": "Quests"
 },
 {
  "nameEn": "Fall into Forever",
  "types": [
   "Voyages"
  ],
  "category": "Quests"
 },
 {
  "nameEn": "Taco Delight",
  "types": [
   "Treasure Hunt"
  ],
  "category": "Quests"
 },
 {
  "nameEn": "Wrath of the Eikons",
  "types": [
   "Gold Saucer"
  ],
  "category": "Dungeons I"
 },
 {
  "nameEn": "Hearts Tread and Trampled",
  "types": [
   "Voyages"
  ],
  "category": "Quests"
 },
 {
  "nameEn": "Persistence",
  "types": [
   "Gold Saucer"
  ],
  "category": "Dungeons I"
 },
 {
  "nameEn": "A Fell Air Falleth",
  "types": [
   "Gold Saucer"
  ],
  "category": "Dungeons I"
 },
 {
  "nameEn": "Dark City Treno (Dawntrail)",
  "types": [
   "Quest"
  ],
  "category": "Locales II"
 },
 {
  "nameEn": "FINAL FANTASY IX: Battle 2 (Dawntrail)",
  "types": [
   "Trial"
  ],
  "category": "Trials"
 },
 {
  "nameEn": "Fanfare from FINAL FANTASY IX",
  "types": [
   "Dungeon"
  ],
  "category": "Dungeons II"
 },
 {
  "nameEn": "FINAL FANTASY IX: Battle 1 (Dawntrail)",
  "types": [
   "Dungeon"
  ],
  "category": "Dungeons II"
 },
 {
  "nameEn": "Ride the Rhythm (Dark Decades)",
  "types": [
   "Premium"
  ],
  "category": "Online Store & Bonuses"
 },
 {
  "nameEn": "Shadowbringers (Dark Decades)",
  "types": [
   "Premium"
  ],
  "category": "Online Store & Bonuses"
 },
 {
  "nameEn": "Snowline Rollick",
  "types": [
   "Tribal"
  ],
  "category": "Locales II"
 },
 {
  "nameEn": "Moment of Peace",
  "types": [
   "Trial"
  ],
  "category": "Others"
 },
 {
  "nameEn": "Kunafa, Windsong Village - Plenty (Day)",
  "types": [
   "Trial"
  ],
  "category": "Others"
 },
 {
  "nameEn": "Radiant Cry of Life",
  "types": [
   "Trial"
  ],
  "category": "Trials"
 },
 {
  "nameEn": "Base Camp (Day)",
  "types": [
   "Trial"
  ],
  "category": "Others"
 },
 {
  "nameEn": "White Wraith",
  "types": [
   "Trial"
  ],
  "category": "Others"
 },
 {
  "nameEn": "Insatiable (Pulse 2)",
  "types": [
   "Deep Dungeon"
  ],
  "category": "Dungeons II"
 },
 {
  "nameEn": "Civilizations (Pulse 2)",
  "types": [
   "Deep Dungeon"
  ],
  "category": "Dungeons II"
 },
 {
  "nameEn": "What Angel Wakes Me (Scions & Sinners: Instrumental)",
  "types": [
   "Quest"
  ],
  "category": "Dungeons II"
 },
 {
  "nameEn": "Shadows Withal (Scions & Sinners: Piano)",
  "types": [
   "Deep Dungeon"
  ],
  "category": "Dungeons II"
 },
 {
  "nameEn": "Rays of Devotion",
  "types": [
   "Deep Dungeon"
  ],
  "category": "Dungeons II"
 },
 {
  "nameEn": "Carrots of Passion",
  "types": [
   "Cosmic Exploration"
  ],
  "category": "Others"
 },
 {
  "nameEn": "Kaleidoscope",
  "types": [
   "Cosmic Exploration"
  ],
  "category": "Others"
 },
 {
  "nameEn": "Sarutabaruta",
  "types": [
   "Raid"
  ],
  "category": "Raids II"
 },
 {
  "nameEn": "Gustaberg",
  "types": [
   "Raid"
  ],
  "category": "Raids II"
 },
 {
  "nameEn": "The Big One",
  "types": [
   "Raid"
  ],
  "category": "Raids II"
 },
 {
  "nameEn": "Vana'diel March #2",
  "types": [
   "Quest"
  ],
  "category": "Raids II"
 },
 {
  "nameEn": "Voyager",
  "types": [
   "Raid"
  ],
  "category": "Raids II"
 },
 {
  "nameEn": "Sometime, Somewhere",
  "types": [
   "Raid"
  ],
  "category": "Raids II"
 },
 {
  "nameEn": "Hopelessness",
  "types": [
   "Raid"
  ],
  "category": "Raids II"
 },
 {
  "nameEn": "Jeweled Boughs",
  "types": [
   "Raid"
  ],
  "category": "Raids II"
 },
 {
  "nameEn": "Despair (Memoro de la S^tono)",
  "types": [
   "Raid"
  ],
  "category": "Raids II"
 },
 {
  "nameEn": "Belief",
  "types": [
   "Raid"
  ],
  "category": "Raids II"
 },
 {
  "nameEn": "Eald'narche",
  "types": [
   "Raid"
  ],
  "category": "Raids II"
 },
 {
  "nameEn": "Tough Battle #2",
  "types": [
   "Raid"
  ],
  "category": "Raids II"
 },
 {
  "nameEn": "Hidden Truths",
  "types": [
   "Raid"
  ],
  "category": "Raids II"
 },
 {
  "nameEn": "Tough Battle",
  "types": [
   "Raid"
  ],
  "category": "Raids II"
 },
 {
  "nameEn": "Ronfaure",
  "types": [
   "Raid"
  ],
  "category": "Raids II"
 },
 {
  "nameEn": "The Promise of Tomorrow",
  "types": [
   "Quest"
  ],
  "category": "Quests"
 },
 {
  "nameEn": "Etched in Memory",
  "types": [
   "Treasure Hunt"
  ],
  "category": "Quests"
 },
 {
  "nameEn": "Coffee Break",
  "types": [
   "Voyages"
  ],
  "category": "Quests"
 },
 {
  "nameEn": "FINAL FANTASY IX: The Final Battle (Dawntrail)",
  "types": [
   "Trial"
  ],
  "category": "Trials"
 },
 {
  "nameEn": "Remembrance",
  "types": [
   "Dungeon"
  ],
  "category": "Dungeons II"
 },
 {
  "nameEn": "Thunder God Cid's Theme",
  "types": [
   "Premium"
  ],
  "category": "Online Store & Bonuses"
 },
 {
  "nameEn": "Brave Story",
  "types": [
   "Premium"
  ],
  "category": "Online Store & Bonuses"
 },
 {
  "nameEn": "Party Composition",
  "types": [
   "Premium"
  ],
  "category": "Online Store & Bonuses"
 },
 {
  "nameEn": "Memories",
  "types": [
   "Premium"
  ],
  "category": "Online Store & Bonuses"
 },
 {
  "nameEn": "Prologue",
  "types": [
   "Premium"
  ],
  "category": "Online Store & Bonuses"
 },
 {
  "nameEn": "Home at Heart",
  "types": [
   "Tribal"
  ],
  "category": "Locales II"
 },
 {
  "nameEn": "Exdeath's Castle (Dawntrail)",
  "types": [
   "Occult Crescent"
  ],
  "category": "Others"
 },
 {
  "nameEn": "A New World (Dawntrail)",
  "types": [
   "Occult Crescent"
  ],
  "category": "Others"
 },
 {
  "nameEn": "FINAL FANTASY V: Battle 1 (Dawntrail)",
  "types": [
   "Occult Crescent"
  ],
  "category": "Others"
 },
 {
  "nameEn": "Garden Ruins",
  "types": [
   "Occult Crescent"
  ],
  "category": "Others"
 },
 {
  "nameEn": "Garden Relics",
  "types": [
   "Occult Crescent"
  ],
  "category": "Others"
 },
 {
  "nameEn": "Town Theme (Dawntrail)",
  "types": [
   "Occult Crescent"
  ],
  "category": "Others"
 },
 {
  "nameEn": "Close in the Distance (Instrumental)",
  "types": [
   "Cosmic Exploration"
  ],
  "category": "Locales II"
 },
 {
  "nameEn": "Echoes in the Distance",
  "types": [
   "Cosmic Exploration"
  ],
  "category": "Locales II"
 },
 {
  "nameEn": "The Airship",
  "types": [
   "Cosmic Exploration"
  ],
  "category": "Others"
 },
 {
  "nameEn": "Hey, Cid!",
  "types": [
   "Cosmic Exploration"
  ],
  "category": "Others"
 },
 {
  "nameEn": "Stargazers",
  "types": [
   "Cosmic Exploration"
  ],
  "category": "Others"
 },
 {
  "nameEn": "Peerless",
  "types": [
   "Raid"
  ],
  "category": "Raids II"
 },
 {
  "nameEn": "Unleashed",
  "types": [
   "Raid"
  ],
  "category": "Raids II"
 },
 {
  "nameEn": "Not Afraid",
  "types": [
   "Raid"
  ],
  "category": "Raids II"
 },
 {
  "nameEn": "Back to the Drawing Board",
  "types": [
   "Raid"
  ],
  "category": "Raids II"
 },
 {
  "nameEn": "Ride the Rhythm",
  "types": [
   "Raid"
  ],
  "category": "Raids II"
 },
 {
  "nameEn": "Mog House",
  "types": [
   "Achievement"
  ],
  "category": "Raids II"
 },
 {
  "nameEn": "Fun and Games",
  "types": [
   "Treasure Hunt"
  ],
  "category": "Quests"
 },
 {
  "nameEn": "In Dawn's Embrace",
  "types": [
   "Voyages"
  ],
  "category": "Quests"
 },
 {
  "nameEn": "Sunset",
  "types": [
   "Wondrous Tails"
  ],
  "category": "Trials"
 },
 {
  "nameEn": "Todoroki",
  "types": [
   "Wondrous Tails"
  ],
  "category": "Trials"
 },
 {
  "nameEn": "Roses of May (Dawntrail)",
  "types": [
   "Crafting"
  ],
  "category": "Trials"
 },
 {
  "nameEn": "Find the Princess (Dawntrail)",
  "types": [
   "Dungeon"
  ],
  "category": "Dungeons II"
 },
 {
  "nameEn": "Bright Bustle",
  "types": [
   "Quest"
  ],
  "category": "Quests"
 },
 {
  "nameEn": "Return to Oblivion (Scions & Sinners: Band)",
  "types": [
   "Achievement"
  ],
  "category": "Raids II"
 },
 {
  "nameEn": "A Sundering of Light",
  "types": [
   "Achievement"
  ],
  "category": "Raids II"
 },
 {
  "nameEn": "Winter's Warm Boughs",
  "types": [
   "Event",
   "Premium"
  ],
  "category": "Seasonal"
 },
 {
  "nameEn": "Vana'diel March",
  "types": [
   "Raid"
  ],
  "category": "Raids II"
 },
 {
  "nameEn": "Awakening",
  "types": [
   "Raid"
  ],
  "category": "Raids II"
 },
 {
  "nameEn": "Castle Zvahl",
  "types": [
   "Raid"
  ],
  "category": "Raids II"
 },
 {
  "nameEn": "Cast Stones in Shadow",
  "types": [
   "Treasure Hunt"
  ],
  "category": "Quests"
 },
 {
  "nameEn": "Fighters of the Crystal",
  "types": [
   "Raid"
  ],
  "category": "Raids II"
 },
 {
  "nameEn": "Nature's Bounty",
  "types": [
   "Voyages"
  ],
  "category": "Quests"
 },
 {
  "nameEn": "Battle Theme from FINAL FANTASY XI",
  "types": [
   "Raid"
  ],
  "category": "Raids II"
 },
 {
  "nameEn": "Tu'Lia",
  "types": [
   "Raid"
  ],
  "category": "Raids II"
 },
 {
  "nameEn": "Battle in the Dungeon #3",
  "types": [
   "Raid"
  ],
  "category": "Raids II"
 },
 {
  "nameEn": "The Travel Agency (Dawntrail)",
  "types": [
   "Tribal"
  ],
  "category": "Locales II"
 },
 {
  "nameEn": "Battle in the Dungeon",
  "types": [
   "Raid"
  ],
  "category": "Raids II"
 },
 {
  "nameEn": "Faerie Battle",
  "types": [
   "FATE"
  ],
  "category": "Locales II"
 },
 {
  "nameEn": "Depths of the Soul",
  "types": [
   "Raid"
  ],
  "category": "Raids II"
 },
 {
  "nameEn": "Echoes of Memory",
  "types": [
   "FATE"
  ],
  "category": "Locales II"
 },
 {
  "nameEn": "Shadow Lord",
  "types": [
   "Raid"
  ],
  "category": "Raids II"
 },
 {
  "nameEn": "Crash in the Dark",
  "types": [
   "FATE"
  ],
  "category": "Locales II"
 },
 {
  "nameEn": "The Forgotten City - Tavnazian Safehold",
  "types": [
   "Raid"
  ],
  "category": "Raids II"
 },
 {
  "nameEn": "Ceruleum Embers by Dusk",
  "types": [
   "FATE"
  ],
  "category": "Locales II"
 },
 {
  "nameEn": "The Grand Duchy of Jeuno",
  "types": [
   "Quest"
  ],
  "category": "Raids II"
 },
 {
  "nameEn": "Skybound Emerald",
  "types": [
   "FATE"
  ],
  "category": "Locales II"
 },
 {
  "nameEn": "Where Dæmons Abide",
  "types": [
   "Quest"
  ],
  "category": "Raids II"
 },
 {
  "nameEn": "Of Glittering Baubles",
  "types": [
   "FATE"
  ],
  "category": "Locales II"
 },
 {
  "nameEn": "Windswept Whispers",
  "types": [
   "FATE"
  ],
  "category": "Locales II"
 },
 {
  "nameEn": "Morrow's Magic",
  "types": [
   "FATE"
  ],
  "category": "Locales II"
 },
 {
  "nameEn": "Paved with Resolve",
  "types": [
   "Crafting"
  ],
  "category": "Trials"
 },
 {
  "nameEn": "Paved in Solitude",
  "types": [
   "Crafting"
  ],
  "category": "Trials"
 },
 {
  "nameEn": "Unbroken Vessels",
  "types": [
   "Dungeon"
  ],
  "category": "Dungeons II"
 },
 {
  "nameEn": "Give It All (Darkest Before Dawn)",
  "types": [
   "Premium"
  ],
  "category": "Online Store & Bonuses"
 },
 {
  "nameEn": "Bee My Honey (Darkest Before Dawn)",
  "types": [
   "Premium"
  ],
  "category": "Online Store & Bonuses"
 },
 {
  "nameEn": "A Risky Bet",
  "types": [
   "Raid"
  ],
  "category": "Raids II"
 },
 {
  "nameEn": "Pathmaker",
  "types": [
   "Treasure Hunt"
  ],
  "category": "Dungeons II"
 },
 {
  "nameEn": "Give It All",
  "types": [
   "Raid"
  ],
  "category": "Raids II"
 },
 {
  "nameEn": "Burning Souls",
  "types": [
   "Raid"
  ],
  "category": "Raids II"
 },
 {
  "nameEn": "Bee My Honey",
  "types": [
   "Raid"
  ],
  "category": "Raids II"
 },
 {
  "nameEn": "It's Showtime!",
  "types": [
   "Raid"
  ],
  "category": "Raids II"
 },
 {
  "nameEn": "Smile",
  "types": [
   "Quest"
  ],
  "category": "Quests"
 },
 {
  "nameEn": "Dawntrail",
  "types": [
   "Quest"
  ],
  "category": "Quests"
 },
 {
  "nameEn": "Blade's Exaltation",
  "types": [
   "Hunts"
  ],
  "category": "Locales II"
 },
 {
  "nameEn": "Desertwalkers",
  "types": [
   "Quest"
  ],
  "category": "Locales II"
 },
 {
  "nameEn": "Life Bound by Honor",
  "types": [
   "Quest"
  ],
  "category": "Locales II"
 },
 {
  "nameEn": "Seeking Purpose",
  "types": [
   "Crafting"
  ],
  "category": "Trials"
 },
 {
  "nameEn": "Pastoral Pleasures",
  "types": [
   "Quest"
  ],
  "category": "Locales II"
 },
 {
  "nameEn": "The Skyruin",
  "types": [
   "Crafting"
  ],
  "category": "Trials"
 },
 {
  "nameEn": "Bygone Serenity",
  "types": [
   "FATE"
  ],
  "category": "Locales II"
 },
 {
  "nameEn": "Flash in the Dark",
  "types": [
   "FATE"
  ],
  "category": "Locales II"
 },
 {
  "nameEn": "Ceruleum Smoke at High Noon",
  "types": [
   "FATE"
  ],
  "category": "Locales II"
 },
 {
  "nameEn": "Emerald under Sapphire",
  "types": [
   "FATE"
  ],
  "category": "Locales II"
 },
 {
  "nameEn": "Of Glittering Wings",
  "types": [
   "FATE"
  ],
  "category": "Locales II"
 },
 {
  "nameEn": "Windswept Echoes",
  "types": [
   "FATE"
  ],
  "category": "Locales II"
 },
 {
  "nameEn": "Starless Skyline",
  "types": [
   "FATE"
  ],
  "category": "Locales II"
 },
 {
  "nameEn": "Morrow's Might",
  "types": [
   "FATE"
  ],
  "category": "Locales II"
 },
 {
  "nameEn": "Roads Forsaken",
  "types": [
   "Treasure Hunt"
  ],
  "category": "Dungeons II"
 },
 {
  "nameEn": "Court Jesters (Dawntrail)",
  "types": [
   "Dungeon"
  ],
  "category": "Dungeons II"
 },
 {
  "nameEn": "Blessings on the Bluffs",
  "types": [
   "Dungeon"
  ],
  "category": "Dungeons II"
 },
 {
  "nameEn": "A Trail Unending",
  "types": [
   "Dungeon"
  ],
  "category": "Dungeons II"
 },
 {
  "nameEn": "Anatomy of Existence",
  "types": [
   "Dungeon"
  ],
  "category": "Dungeons II"
 },
 {
  "nameEn": "In Fulgur and Fire",
  "types": [
   "Dungeon"
  ],
  "category": "Dungeons II"
 },
 {
  "nameEn": "Lost in the Deep",
  "types": [
   "Dungeon"
  ],
  "category": "Dungeons II"
 },
 {
  "nameEn": "Empyrean Peak",
  "types": [
   "Dungeon"
  ],
  "category": "Dungeons II"
 },
 {
  "nameEn": "Punutiy Crossing",
  "types": [
   "Dungeon"
  ],
  "category": "Dungeons II"
 },
 {
  "nameEn": "Tinkerer's Treasure Trove",
  "types": [
   "Voyages"
  ],
  "category": "Ambient"
 },
 {
  "nameEn": "Subterranean Drop",
  "types": [
   "Voyages"
  ],
  "category": "Ambient"
 },
 {
  "nameEn": "Endwalker – Footfalls (Fan Fest)",
  "types": [
   "Premium"
  ],
  "category": "Online Store & Bonuses"
 },
 {
  "nameEn": "Flow (Fan Fest)",
  "types": [
   "Premium"
  ],
  "category": "Online Store & Bonuses"
 },
 {
  "nameEn": "Land of Eikons",
  "types": [
   "Gold Saucer"
  ],
  "category": "Seasonal"
 },
 {
  "nameEn": "Find the Flame",
  "types": [
   "Gold Saucer"
  ],
  "category": "Seasonal"
 },
 {
  "nameEn": "To Sail Forbidden Seas",
  "types": [
   "Gold Saucer"
  ],
  "category": "Seasonal"
 },
 {
  "nameEn": "Away (Refrain)",
  "types": [
   "Gold Saucer"
  ],
  "category": "Seasonal"
 },
 {
  "nameEn": "Who I Really Am",
  "types": [
   "Gold Saucer"
  ],
  "category": "Seasonal"
 },
 {
  "nameEn": "The State of the Realm",
  "types": [
   "Gold Saucer"
  ],
  "category": "Seasonal"
 },
 {
  "nameEn": "Before the Storm - Caer Norvent",
  "types": [
   "Gold Saucer"
  ],
  "category": "Seasonal"
 },
 {
  "nameEn": "Forevermore - The Grand Duchy of Rosaria",
  "types": [
   "Gold Saucer"
  ],
  "category": "Seasonal"
 },
 {
  "nameEn": "Idylls of the Empire",
  "types": [
   "Gold Saucer"
  ],
  "category": "Seasonal"
 },
 {
  "nameEn": "Tonitrua ex Machina",
  "types": [
   "Gold Saucer"
  ],
  "category": "Seasonal"
 },
 {
  "nameEn": "A Gentleman to Walk with Me",
  "types": [
   "Quest"
  ],
  "category": "Quests"
 },
 {
  "nameEn": "O Hunter, Rejoice",
  "types": [
   "V&C Dungeon"
  ],
  "category": "Dungeons II"
 },
 {
  "nameEn": "O Speaker, Slumber",
  "types": [
   "V&C Dungeon"
  ],
  "category": "Dungeons II"
 },
 {
  "nameEn": "Everybody Falls (Fall Guys Theme)",
  "types": [
   "Event"
  ],
  "category": "Seasonal"
 },
 {
  "nameEn": "From Fear to Fortitude",
  "types": [
   "Voyages"
  ],
  "category": "Quests"
 },
 {
  "nameEn": "Pennons Aloft",
  "types": [
   "Voyages"
  ],
  "category": "Quests"
 },
 {
  "nameEn": "Myths of the Realm",
  "types": [
   "Raid"
  ],
  "category": "Raids II"
 },
 {
  "nameEn": "Course Uncharted",
  "types": [
   "Raid"
  ],
  "category": "Raids II"
 },
 {
  "nameEn": "The Red Wings (Endwalker)",
  "types": [
   "Crafting"
  ],
  "category": "Trials"
 },
 {
  "nameEn": "Fair Winds to Guide",
  "types": [
   "Raid"
  ],
  "category": "Raids II"
 },
 {
  "nameEn": "FINAL FANTASY IV: The Final Battle (Endwalker)",
  "types": [
   "Crafting"
  ],
  "category": "Trials"
 },
 {
  "nameEn": "One among Wonders",
  "types": [
   "Quest"
  ],
  "category": "Raids II"
 },
 {
  "nameEn": "Kingdom of Baron (Endwalker)",
  "types": [
   "Dungeon"
  ],
  "category": "Dungeons II"
 },
 {
  "nameEn": "In the Balance (Amanda Achen Vocals)",
  "types": [
   "Premium"
  ],
  "category": "Online Store & Bonuses"
 },
 {
  "nameEn": "Dedicated to Moonlight (Forge Ahead)",
  "types": [
   "Premium"
  ],
  "category": "Online Store & Bonuses"
 },
 {
  "nameEn": "Dedicated to Moonlight (Amanda Achen Vocals)",
  "types": [
   "Premium"
  ],
  "category": "Online Store & Bonuses"
 },
 {
  "nameEn": "The Labyrinth (Forge Ahead)",
  "types": [
   "Premium"
  ],
  "category": "Online Store & Bonuses"
 },
 {
  "nameEn": "Carrots of Happiness (Forge Ahead)",
  "types": [
   "Premium"
  ],
  "category": "Online Store & Bonuses"
 },
 {
  "nameEn": "What Once Was (Forge Ahead)",
  "types": [
   "Premium"
  ],
  "category": "Online Store & Bonuses"
 },
 {
  "nameEn": "Flow (Forge Ahead)",
  "types": [
   "Premium"
  ],
  "category": "Online Store & Bonuses"
 },
 {
  "nameEn": "Athena, the Tireless One (Forge Ahead)",
  "types": [
   "Premium"
  ],
  "category": "Online Store & Bonuses"
 },
 {
  "nameEn": "In the Balance (Forge Ahead)",
  "types": [
   "Premium"
  ],
  "category": "Online Store & Bonuses"
 },
 {
  "nameEn": "Scream (Forge Ahead)",
  "types": [
   "Premium"
  ],
  "category": "Online Store & Bonuses"
 },
 {
  "nameEn": "White Stone Black (Forge Ahead)",
  "types": [
   "Premium"
  ],
  "category": "Online Store & Bonuses"
 },
 {
  "nameEn": "To the Edge (Forge Ahead)",
  "types": [
   "Premium"
  ],
  "category": "Online Store & Bonuses"
 },
 {
  "nameEn": "Pom from the Heavens",
  "types": [
   "Event",
   "Premium"
  ],
  "category": "Seasonal"
 },
 {
  "nameEn": "The Land Reborn",
  "types": [
   "Event",
   "Premium"
  ],
  "category": "Seasonal"
 },
 {
  "nameEn": "Looping in the Deepest Fringes",
  "types": [
   "V&C Dungeon"
  ],
  "category": "Locales I"
 },
 {
  "nameEn": "Battle 2 from FINAL FANTASY III",
  "types": [
   "Quest",
   "Hunts"
  ],
  "category": "Others"
 },
 {
  "nameEn": "Crimson Rise",
  "types": [
   "V&C Dungeon"
  ],
  "category": "Dungeons II"
 },
 {
  "nameEn": "My Soul to Keep",
  "types": [
   "Achievement"
  ],
  "category": "Dungeons I"
 },
 {
  "nameEn": "Meteor",
  "types": [
   "Achievement"
  ],
  "category": "Quests"
 },
 {
  "nameEn": "Tranquility",
  "types": [
   "Purchase"
  ],
  "category": "Quests"
 },
 {
  "nameEn": "Skullduggery",
  "types": [
   "Purchase"
  ],
  "category": "Quests"
 },
 {
  "nameEn": "Damnation",
  "types": [
   "Purchase"
  ],
  "category": "Quests"
 },
 {
  "nameEn": "Machinations",
  "types": [
   "Purchase"
  ],
  "category": "Quests"
 },
 {
  "nameEn": "Kiss of Chaos",
  "types": [
   "Purchase"
  ],
  "category": "Quests"
 },
 {
  "nameEn": "Return of the Hero",
  "types": [
   "Purchase"
  ],
  "category": "Quests"
 },
 {
  "nameEn": "Conundrum",
  "types": [
   "Purchase"
  ],
  "category": "Quests"
 },
 {
  "nameEn": "Fracture",
  "types": [
   "Purchase"
  ],
  "category": "Quests"
 },
 {
  "nameEn": "Voidcast Savior",
  "types": [
   "Crafting"
  ],
  "category": "Trials"
 },
 {
  "nameEn": "Ultima's Perfection (Endwalker)",
  "types": [
   "Raid"
  ],
  "category": "Raids II"
 },
 {
  "nameEn": "Athena, the Tireless One",
  "types": [
   "Raid"
  ],
  "category": "Raids II"
 },
 {
  "nameEn": "Fleeting Moment",
  "types": [
   "Raid"
  ],
  "category": "Raids II"
 },
 {
  "nameEn": "One Amongst the Weary",
  "types": [
   "Raid"
  ],
  "category": "Raids II"
 },
 {
  "nameEn": "Subterranean Sanctuary",
  "types": [
   "Island Sanctuary"
  ],
  "category": "Others"
 },
 {
  "nameEn": "Another Moon",
  "types": [
   "Quest"
  ],
  "category": "Locales II"
 },
 {
  "nameEn": "Starsbreath",
  "types": [
   "Dungeon"
  ],
  "category": "Dungeons II"
 },
 {
  "nameEn": "A Long Fall (Pulse)",
  "types": [
   "Premium"
  ],
  "category": "Online Store & Bonuses"
 },
 {
  "nameEn": "I Am the Sea (Pulse)",
  "types": [
   "Premium"
  ],
  "category": "Online Store & Bonuses"
 },
 {
  "nameEn": "Beauty's Wicked Wiles (Pulse)",
  "types": [
   "Premium"
  ],
  "category": "Online Store & Bonuses"
 },
 {
  "nameEn": "Equilibrium (Pulse)",
  "types": [
   "Premium"
  ],
  "category": "Online Store & Bonuses"
 },
 {
  "nameEn": "Unbreakable (Pulse)",
  "types": [
   "Premium"
  ],
  "category": "Online Store & Bonuses"
 },
 {
  "nameEn": "The Final Day (Orchestral Version)",
  "types": [
   "Premium"
  ],
  "category": "Online Store & Bonuses"
 },
 {
  "nameEn": "Close in the Distance (Orchestral Version)",
  "types": [
   "Premium"
  ],
  "category": "Online Store & Bonuses"
 },
 {
  "nameEn": "Your Answer (Orchestral Version)",
  "types": [
   "Premium"
  ],
  "category": "Online Store & Bonuses"
 },
 {
  "nameEn": "Endcaller (Orchestral Version)",
  "types": [
   "Premium"
  ],
  "category": "Online Store & Bonuses"
 },
 {
  "nameEn": "Shadowbringers (Orchestral Version)",
  "types": [
   "Premium"
  ],
  "category": "Online Store & Bonuses"
 },
 {
  "nameEn": "Crystal Rain",
  "types": [
   "Deep Dungeon"
  ],
  "category": "Locales I"
 },
 {
  "nameEn": "The Promise of Plunder",
  "types": [
   "Deep Dungeon"
  ],
  "category": "Dungeons I"
 },
 {
  "nameEn": "Battle 1 from FINAL FANTASY IV",
  "types": [
   "Tribal"
  ],
  "category": "Locales II"
 },
 {
  "nameEn": "Dreamwalker",
  "types": [
   "Tribal"
  ],
  "category": "Locales II"
 },
 {
  "nameEn": "Forbidden Land (Endwalker)",
  "types": [
   "Deep Dungeon"
  ],
  "category": "Dungeons II"
 },
 {
  "nameEn": "Dangertek",
  "types": [
   "Treasure Hunt"
  ],
  "category": "Dungeons I"
 },
 {
  "nameEn": "Holy Consult",
  "types": [
   "Dungeon"
  ],
  "category": "Dungeons I"
 },
 {
  "nameEn": "Forgotten by the Sun",
  "types": [
   "Dungeon"
  ],
  "category": "Dungeons I"
 },
 {
  "nameEn": "Cracks in the Wall",
  "types": [
   "Dungeon"
  ],
  "category": "Dungeons I"
 },
 {
  "nameEn": "Miser's Folly",
  "types": [
   "Dungeon"
  ],
  "category": "Dungeons I"
 },
 {
  "nameEn": "Cold Salvation",
  "types": [
   "Dungeon"
  ],
  "category": "Dungeons I"
 },
 {
  "nameEn": "Echoes of Ages Past",
  "types": [
   "Dungeon"
  ],
  "category": "Dungeons I"
 },
 {
  "nameEn": "Somewhere in the World (Ambitions Writhe)",
  "types": [
   "Quest"
  ],
  "category": "Quests"
 },
 {
  "nameEn": "Dreams Aloft",
  "types": [
   "Voyages"
  ],
  "category": "Quests"
 },
 {
  "nameEn": "Sacred Bonds",
  "types": [
   "Purchase"
  ],
  "category": "Quests"
 },
 {
  "nameEn": "Bliss",
  "types": [
   "Purchase"
  ],
  "category": "Quests"
 },
 {
  "nameEn": "Forged in Crimson",
  "types": [
   "Crafting"
  ],
  "category": "Trials"
 },
 {
  "nameEn": "A Victory Fanfare Reborn",
  "types": [
   "Treasure Hunt"
  ],
  "category": "Others"
 },
 {
  "nameEn": "Dedicated to Moonlight",
  "types": [
   "Raid"
  ],
  "category": "Raids II"
 },
 {
  "nameEn": "Rhythm of the Realm",
  "types": [
   "Raid"
  ],
  "category": "Raids II"
 },
 {
  "nameEn": "Favor",
  "types": [
   "Raid"
  ],
  "category": "Raids II"
 },
 {
  "nameEn": "Deep Blue",
  "types": [
   "Dungeon"
  ],
  "category": "Dungeons II"
 },
 {
  "nameEn": "Flow (Orchestral Version)",
  "types": [
   "Premium"
  ],
  "category": "Online Store & Bonuses"
 },
 {
  "nameEn": "To the Edge (Orchestral Version)",
  "types": [
   "Premium"
  ],
  "category": "Online Store & Bonuses"
 },
 {
  "nameEn": "Pa-Paya Demastered",
  "types": [
   "Event",
   "Premium"
  ],
  "category": "Seasonal"
 },
 {
  "nameEn": "Decisions",
  "types": [
   "Event",
   "Premium"
  ],
  "category": "Seasonal"
 },
 {
  "nameEn": "Cradle of Hope",
  "types": [
   "Tribal"
  ],
  "category": "Locales II"
 },
 {
  "nameEn": "Desert Sun",
  "types": [
   "V&C Dungeon"
  ],
  "category": "Dungeons II"
 },
 {
  "nameEn": "The Hall of Flames",
  "types": [
   "Purchase"
  ],
  "category": "Locales I"
 },
 {
  "nameEn": "Maelstrom Command",
  "types": [
   "Purchase"
  ],
  "category": "Locales I"
 },
 {
  "nameEn": "Into the Adder's Den",
  "types": [
   "Purchase"
  ],
  "category": "Locales I"
 },
 {
  "nameEn": "Unworthy",
  "types": [
   "Skybuilders"
  ],
  "category": "Trials"
 },
 {
  "nameEn": "Battle with the Four Fiends (Buried Memory)",
  "types": [
   "Crafting"
  ],
  "category": "Trials"
 },
 {
  "nameEn": "Island Paradise",
  "types": [
   "Island Sanctuary"
  ],
  "category": "Others"
 },
 {
  "nameEn": "A Quiet Moment",
  "types": [
   "Island Sanctuary"
  ],
  "category": "Others"
 },
 {
  "nameEn": "White Stone Black",
  "types": [
   "Raid"
  ],
  "category": "Raids II"
 },
 {
  "nameEn": "Embers",
  "types": [
   "Raid"
  ],
  "category": "Raids II"
 },
 {
  "nameEn": "Scream",
  "types": [
   "Raid"
  ],
  "category": "Raids II"
 },
 {
  "nameEn": "Silent Scream",
  "types": [
   "Raid"
  ],
  "category": "Raids II"
 },
 {
  "nameEn": "Stigma",
  "types": [
   "Dungeon"
  ],
  "category": "Dungeons I"
 },
 {
  "nameEn": "Toll of the Bells",
  "types": [
   "Dungeon"
  ],
  "category": "Dungeons I"
 },
 {
  "nameEn": "FINAL FANTASY IV: Battle 2 (Endwalker)",
  "types": [
   "Dungeon"
  ],
  "category": "Dungeons II"
 },
 {
  "nameEn": "Troian Beauty (Endwalker)",
  "types": [
   "Dungeon",
   "Deep Dungeon"
  ],
  "category": "Dungeons II"
 },
 {
  "nameEn": "Shuffle or Boogie",
  "types": [
   "Gold Saucer"
  ],
  "category": "Others"
 },
 {
  "nameEn": "Silence",
  "types": [
   "Purchase"
  ],
  "category": "Ambient"
 },
 {
  "nameEn": "Penitus",
  "types": [
   "FATE"
  ],
  "category": "Dungeons I"
 },
 {
  "nameEn": "The Emperor's Wont",
  "types": [
   "FATE"
  ],
  "category": "Dungeons I"
 },
 {
  "nameEn": "The Sands' Secrets",
  "types": [
   "Purchase"
  ],
  "category": "Quests"
 },
 {
  "nameEn": "Ripples in the Sea",
  "types": [
   "Purchase"
  ],
  "category": "Quests"
 },
 {
  "nameEn": "Lipflaps on Longstops",
  "types": [
   "Dungeon"
  ],
  "category": "Dungeons I"
 },
 {
  "nameEn": "Dewdrops & Moonbeams",
  "types": [
   "Purchase"
  ],
  "category": "Quests"
 },
 {
  "nameEn": "A Thousand Screams",
  "types": [
   "Dungeon"
  ],
  "category": "Dungeons I"
 },
 {
  "nameEn": "Born to Ride",
  "types": [
   "Purchase"
  ],
  "category": "Others"
 },
 {
  "nameEn": "Hic Svnt Leones (Beyond the Shadow)",
  "types": [
   "Premium"
  ],
  "category": "Online Store & Bonuses"
 },
 {
  "nameEn": "Close in the Distance (Beyond the Shadow)",
  "types": [
   "Premium"
  ],
  "category": "Online Store & Bonuses"
 },
 {
  "nameEn": "Flow Together",
  "types": [
   "Quest"
  ],
  "category": "Quests"
 },
 {
  "nameEn": "Hippo Ridin'",
  "types": [
   "Tribal"
  ],
  "category": "Locales II"
 },
 {
  "nameEn": "Home Beyond the Horizon",
  "types": [
   "FATE"
  ],
  "category": "Quests"
 },
 {
  "nameEn": "With Hearts Aligned",
  "types": [
   "Crafting"
  ],
  "category": "Trials"
 },
 {
  "nameEn": "The Final Day",
  "types": [
   "Crafting"
  ],
  "category": "Trials"
 },
 {
  "nameEn": "Welcome to Our Town! (Endwalker)",
  "types": [
   "FATE"
  ],
  "category": "Locales II"
 },
 {
  "nameEn": "Stars Long Dead",
  "types": [
   "FATE"
  ],
  "category": "Locales II"
 },
 {
  "nameEn": "In the Balance",
  "types": [
   "Raid"
  ],
  "category": "Raids II"
 },
 {
  "nameEn": "Black Steel, Cold Embers",
  "types": [
   "FATE"
  ],
  "category": "Locales II"
 },
 {
  "nameEn": "Radiance",
  "types": [
   "Raid"
  ],
  "category": "Raids II"
 },
 {
  "nameEn": "Prayers Repeated",
  "types": [
   "FATE"
  ],
  "category": "Locales II"
 },
 {
  "nameEn": "Pilgrimage",
  "types": [
   "Raid"
  ],
  "category": "Raids II"
 },
 {
  "nameEn": "Like a Summer Rain",
  "types": [
   "Dungeon"
  ],
  "category": "Dungeons I"
 },
 {
  "nameEn": "Dreams of Man",
  "types": [
   "FATE"
  ],
  "category": "Locales II"
 },
 {
  "nameEn": "Perfumed Eves",
  "types": [
   "FATE"
  ],
  "category": "Locales II"
 },
 {
  "nameEn": "Vibrant Voices",
  "types": [
   "FATE"
  ],
  "category": "Locales II"
 },
 {
  "nameEn": "The Day Will Come (Endwalker)",
  "types": [
   "FATE"
  ],
  "category": "Locales II"
 },
 {
  "nameEn": "The Nautilus Knoweth",
  "types": [
   "FATE"
  ],
  "category": "Locales II"
 },
 {
  "nameEn": "Descent",
  "types": [
   "Dungeon"
  ],
  "category": "Dungeons I"
 },
 {
  "nameEn": "Aftermath",
  "types": [
   "Dungeon"
  ],
  "category": "Dungeons I"
 },
 {
  "nameEn": "The Map Unfolds",
  "types": [
   "Dungeon",
   "Deep Dungeon"
  ],
  "category": "Dungeons II"
 },
 {
  "nameEn": "Gateway to Paradise",
  "types": [
   "Gold Saucer"
  ],
  "category": "Others"
 },
 {
  "nameEn": "Run! (Endwalker)",
  "types": [
   "PvP"
  ],
  "category": "Others"
 },
 {
  "nameEn": "Festival of the Hunt (Endwalker)",
  "types": [
   "PvP"
  ],
  "category": "Others"
 },
 {
  "nameEn": "Warming Up",
  "types": [
   "PvP"
  ],
  "category": "Others"
 },
 {
  "nameEn": "Starlight and Sellswords",
  "types": [
   "Purchase"
  ],
  "category": "Quests"
 },
 {
  "nameEn": "Crimson Sunset (Piano Collections)",
  "types": [
   "Premium"
  ],
  "category": "Online Store & Bonuses"
 },
 {
  "nameEn": "Imagination (Piano Collections)",
  "types": [
   "Premium"
  ],
  "category": "Online Store & Bonuses"
 },
 {
  "nameEn": "Westward Tide (Piano Collections)",
  "types": [
   "Premium"
  ],
  "category": "Online Store & Bonuses"
 },
 {
  "nameEn": "Finality",
  "types": [
   "Treasure Hunt"
  ],
  "category": "Dungeons II"
 },
 {
  "nameEn": "On Blade's Edge",
  "types": [
   "Treasure Hunt"
  ],
  "category": "Dungeons II"
 },
 {
  "nameEn": "Hic Svnt Leones",
  "types": [
   "Raid"
  ],
  "category": "Raids II"
 },
 {
  "nameEn": "Ancient Shackles",
  "types": [
   "Raid"
  ],
  "category": "Raids II"
 },
 {
  "nameEn": "Dawnbound",
  "types": [
   "Dungeon"
  ],
  "category": "Dungeons I"
 },
 {
  "nameEn": "Flow",
  "types": [
   "Quest"
  ],
  "category": "Quests"
 },
 {
  "nameEn": "Endwalker – Footfalls",
  "types": [
   "Quest"
  ],
  "category": "Quests"
 },
 {
  "nameEn": "Your Answer",
  "types": [
   "Crafting"
  ],
  "category": "Trials"
 },
 {
  "nameEn": "Endcaller",
  "types": [
   "Crafting"
  ],
  "category": "Trials"
 },
 {
  "nameEn": "Unbowed",
  "types": [
   "Hunts"
  ],
  "category": "Locales II"
 },
 {
  "nameEn": "Roar of the Wyrm",
  "types": [
   "Dungeon"
  ],
  "category": "Dungeons I"
 },
 {
  "nameEn": "Close in the Distance",
  "types": [
   "FATE"
  ],
  "category": "Locales II"
 },
 {
  "nameEn": "Sky Unsundered",
  "types": [
   "FATE"
  ],
  "category": "Locales II"
 },
 {
  "nameEn": "One Small Step",
  "types": [
   "FATE"
  ],
  "category": "Locales II"
 },
 {
  "nameEn": "White Snow, Black Steel",
  "types": [
   "FATE"
  ],
  "category": "Locales II"
 },
 {
  "nameEn": "Divine Words",
  "types": [
   "FATE"
  ],
  "category": "Locales II"
 },
 {
  "nameEn": "The Labyrinth",
  "types": [
   "FATE"
  ],
  "category": "Locales II"
 },
 {
  "nameEn": "Twilit Terraces",
  "types": [
   "FATE"
  ],
  "category": "Locales II"
 },
 {
  "nameEn": "The Ewer Brimmeth",
  "types": [
   "FATE"
  ],
  "category": "Locales II"
 },
 {
  "nameEn": "Carrots of Happiness",
  "types": [
   "Dungeon",
   "Deep Dungeon"
  ],
  "category": "Dungeons II"
 },
 {
  "nameEn": "Of Countless Stars",
  "types": [
   "Dungeon",
   "Deep Dungeon"
  ],
  "category": "Dungeons II"
 },
 {
  "nameEn": "The Aetherial Sea",
  "types": [
   "Dungeon",
   "Deep Dungeon"
  ],
  "category": "Dungeons II"
 },
 {
  "nameEn": "Miracle Works",
  "types": [
   "Dungeon",
   "Deep Dungeon"
  ],
  "category": "Dungeons II"
 },
 {
  "nameEn": "As the Sky Burns",
  "types": [
   "Dungeon",
   "Deep Dungeon"
  ],
  "category": "Dungeons II"
 },
 {
  "nameEn": "Garlemald Express",
  "types": [
   "Dungeon",
   "Deep Dungeon"
  ],
  "category": "Dungeons II"
 },
 {
  "nameEn": "Tower of Zot (Endwalker)",
  "types": [
   "Dungeon",
   "Deep Dungeon"
  ],
  "category": "Dungeons II"
 },
 {
  "nameEn": "From the Depths",
  "types": [
   "Dungeon"
  ],
  "category": "Dungeons I"
 },
 {
  "nameEn": "Old Wounds (Piano Collections)",
  "types": [
   "Premium"
  ],
  "category": "Online Store & Bonuses"
 },
 {
  "nameEn": "Heroes (Piano Collections)",
  "types": [
   "Premium"
  ],
  "category": "Online Store & Bonuses"
 },
 {
  "nameEn": "Ink Long Dry (Piano Collections)",
  "types": [
   "Premium"
  ],
  "category": "Online Store & Bonuses"
 },
 {
  "nameEn": "Wrath of the Harrier",
  "types": [
   "Bozja"
  ],
  "category": "Others"
 },
 {
  "nameEn": "Weight of the World (Instrumental)",
  "types": [
   "Quest"
  ],
  "category": "Raids II"
 },
 {
  "nameEn": "What Is Love?",
  "types": [
   "Skybuilders"
  ],
  "category": "Locales I"
 },
 {
  "nameEn": "In the Arms of War",
  "types": [
   "Crafting"
  ],
  "category": "Trials"
 },
 {
  "nameEn": "A Better Tomorrow",
  "types": [
   "Treasure Hunt",
   "Deep Dungeon"
  ],
  "category": "Quests"
 },
 {
  "nameEn": "And Love You Shall Find",
  "types": [
   "Quest"
  ],
  "category": "Quests"
 },
 {
  "nameEn": "Faltering Prayer (Dawn Breeze)",
  "types": [
   "Quest"
  ],
  "category": "Raids II"
 },
 {
  "nameEn": "Skyrise",
  "types": [
   "Skybuilders"
  ],
  "category": "Others"
 },
 {
  "nameEn": "Possessed by Disease",
  "types": [
   "Quest"
  ],
  "category": "Raids II"
 },
 {
  "nameEn": "Widespread Illness",
  "types": [
   "Quest"
  ],
  "category": "Raids II"
 },
 {
  "nameEn": "The Color of Depression",
  "types": [
   "Quest"
  ],
  "category": "Raids II"
 },
 {
  "nameEn": "Voice of no Return (Normal)",
  "types": [
   "Quest"
  ],
  "category": "Raids II"
 },
 {
  "nameEn": "Kainé (Final Fantasy Main Theme Version)",
  "types": [
   "Raid"
  ],
  "category": "Raids II"
 },
 {
  "nameEn": "The Sound of the End: 8bit",
  "types": [
   "Raid"
  ],
  "category": "Raids II"
 },
 {
  "nameEn": "The Sound of the End",
  "types": [
   "Raid"
  ],
  "category": "Raids II"
 },
 {
  "nameEn": "Emil (Despair)",
  "types": [
   "Raid"
  ],
  "category": "Raids II"
 },
 {
  "nameEn": "Mourning",
  "types": [
   "Raid"
  ],
  "category": "Raids II"
 },
 {
  "nameEn": "Freedom",
  "types": [
   "Gathering"
  ],
  "category": "Quests"
 },
 {
  "nameEn": "Seven Flames",
  "types": [
   "Dungeon",
   "Deep Dungeon"
  ],
  "category": "Dungeons II"
 },
 {
  "nameEn": "By Design",
  "types": [
   "Voyages"
  ],
  "category": "Quests"
 },
 {
  "nameEn": "Sunrise (Pulse)",
  "types": [
   "Premium"
  ],
  "category": "Online Store & Bonuses"
 },
 {
  "nameEn": "What Angel Wakes Me (Pulse)",
  "types": [
   "Premium"
  ],
  "category": "Online Store & Bonuses"
 },
 {
  "nameEn": "Neath Dark Waters (Pulse)",
  "types": [
   "Premium"
  ],
  "category": "Online Store & Bonuses"
 },
 {
  "nameEn": "Through the Maelstrom (Pulse)",
  "types": [
   "Premium"
  ],
  "category": "Online Store & Bonuses"
 },
 {
  "nameEn": "Rise (Pulse)",
  "types": [
   "Premium"
  ],
  "category": "Online Store & Bonuses"
 },
 {
  "nameEn": "Insatiable (Scions & Sinners: Band)",
  "types": [
   "Premium"
  ],
  "category": "Online Store & Bonuses"
 },
 {
  "nameEn": "Blinding Indigo (Scions & Sinners: Band)",
  "types": [
   "Premium"
  ],
  "category": "Online Store & Bonuses"
 },
 {
  "nameEn": "Shadowbringers (Scions & Sinners: Band)",
  "types": [
   "Premium"
  ],
  "category": "Online Store & Bonuses"
 },
 {
  "nameEn": "What Angel Wakes Me (Scions & Sinners: Band)",
  "types": [
   "Premium"
  ],
  "category": "Online Store & Bonuses"
 },
 {
  "nameEn": "Equilibrium (Scions & Sinners: Band)",
  "types": [
   "Premium"
  ],
  "category": "Online Store & Bonuses"
 },
 {
  "nameEn": "A Long Fall (Scions & Sinners: Piano)",
  "types": [
   "Premium"
  ],
  "category": "Online Store & Bonuses"
 },
 {
  "nameEn": "What Angel Wakes Me (Scions & Sinners: Amanda Achen Vocals)",
  "types": [
   "Premium"
  ],
  "category": "Online Store & Bonuses"
 },
 {
  "nameEn": "Return to Oblivion (Scions & Sinners: Amanda Achen Vocals)",
  "types": [
   "Premium"
  ],
  "category": "Online Store & Bonuses"
 },
 {
  "nameEn": "Tomorrow and Tomorrow (Scions & Sinners: Amanda Achen Vocals)",
  "types": [
   "Premium"
  ],
  "category": "Online Store & Bonuses"
 },
 {
  "nameEn": "Invincible (Scions & Sinners: Piano)",
  "types": [
   "Premium"
  ],
  "category": "Online Store & Bonuses"
 },
 {
  "nameEn": "To the Sun (Piano Collections)",
  "types": [
   "Premium"
  ],
  "category": "Online Store & Bonuses"
 },
 {
  "nameEn": "Serenity (Piano Collections)",
  "types": [
   "Premium"
  ],
  "category": "Online Store & Bonuses"
 },
 {
  "nameEn": "On Westerly Winds (Piano Collections)",
  "types": [
   "Premium"
  ],
  "category": "Online Store & Bonuses"
 },
 {
  "nameEn": "The Queen Awakens",
  "types": [
   "Bozja"
  ],
  "category": "Others"
 },
 {
  "nameEn": "Giving Chase (Zodiac Age Version)",
  "types": [
   "Bozja"
  ],
  "category": "Others"
 },
 {
  "nameEn": "The Sochen Cave Palace (Zodiac Age Version)",
  "types": [
   "Bozja"
  ],
  "category": "Others"
 },
 {
  "nameEn": "Gogo's Theme",
  "types": [
   "Quest",
   "Hunts"
  ],
  "category": "Others"
 },
 {
  "nameEn": "Painted Skies",
  "types": [
   "Skybuilders"
  ],
  "category": "Locales I"
 },
 {
  "nameEn": "Faith in Her Fury",
  "types": [
   "Skybuilders"
  ],
  "category": "Trials"
 },
 {
  "nameEn": "Hearthward",
  "types": [
   "Skybuilders"
  ],
  "category": "Others"
 },
 {
  "nameEn": "New Foundations",
  "types": [
   "Quest"
  ],
  "category": "Others"
 },
 {
  "nameEn": "Dancing Calcabrina",
  "types": [
   "Dungeon"
  ],
  "category": "Dungeons I"
 },
 {
  "nameEn": "The Black Wolf Stalks Again",
  "types": [
   "Crafting"
  ],
  "category": "Trials"
 },
 {
  "nameEn": "Dangerous Words",
  "types": [
   "Treasure Hunt"
  ],
  "category": "Quests"
 },
 {
  "nameEn": "Tomorrow and Tomorrow - Reprise",
  "types": [
   "Treasure Hunt",
   "Deep Dungeon"
  ],
  "category": "Quests"
 },
 {
  "nameEn": "Everywhere and Nowhere",
  "types": [
   "Treasure Hunt"
  ],
  "category": "Quests"
 },
 {
  "nameEn": "Nemesis",
  "types": [
   "Voyages"
  ],
  "category": "Dungeons I"
 },
 {
  "nameEn": "The Extreme (Shadowbringers)",
  "types": [
   "Raid"
  ],
  "category": "Raids II"
 },
 {
  "nameEn": "A Fine Death",
  "types": [
   "Gold Saucer"
  ],
  "category": "Dungeons I"
 },
 {
  "nameEn": "Unmatching Pieces",
  "types": [
   "Treasure Hunt"
  ],
  "category": "Locales II"
 },
 {
  "nameEn": "Promises to Keep",
  "types": [
   "Raid"
  ],
  "category": "Raids II"
 },
 {
  "nameEn": "The Legendary Beast (Shadowbringers)",
  "types": [
   "Raid"
  ],
  "category": "Raids II"
 },
 {
  "nameEn": "Don't Be Afraid (Shadowbringers)",
  "types": [
   "Raid"
  ],
  "category": "Raids II"
 },
 {
  "nameEn": "Shuffle or Boogie (Shadowbringers)",
  "types": [
   "Achievement"
  ],
  "category": "Others"
 },
 {
  "nameEn": "Freshly Glazed Porxie",
  "types": [
   "Dungeon",
   "Deep Dungeon"
  ],
  "category": "Dungeons II"
 },
 {
  "nameEn": "The Ludus",
  "types": [
   "Dungeon"
  ],
  "category": "Dungeons I"
 },
 {
  "nameEn": "Below",
  "types": [
   "Dungeon"
  ],
  "category": "Dungeons I"
 },
 {
  "nameEn": "Painted Foothills (Piano Collections)",
  "types": [
   "Premium"
  ],
  "category": "Online Store & Bonuses"
 },
 {
  "nameEn": "Night in the Brume (Piano Collections)",
  "types": [
   "Premium"
  ],
  "category": "Online Store & Bonuses"
 },
 {
  "nameEn": "Ominous Prognisticks (Piano Collections)",
  "types": [
   "Premium"
  ],
  "category": "Online Store & Bonuses"
 },
 {
  "nameEn": "A Long Fall (Scions & Sinners: Band)",
  "types": [
   "Premium"
  ],
  "category": "Online Store & Bonuses"
 },
 {
  "nameEn": "Neath Dark Waters (Scions & Sinners)",
  "types": [
   "Premium"
  ],
  "category": "Online Store & Bonuses"
 },
 {
  "nameEn": "Life and Death (Zodiac Age Version)",
  "types": [
   "Bozja"
  ],
  "category": "Others"
 },
 {
  "nameEn": "Battle with an Esper (Zodiac Age Version)",
  "types": [
   "Bozja"
  ],
  "category": "Others"
 },
 {
  "nameEn": "Into the Fortress (Zodiac Age Version)",
  "types": [
   "Bozja"
  ],
  "category": "Others"
 },
 {
  "nameEn": "Discord: Imperial (Zodiac Age Version)",
  "types": [
   "Bozja"
  ],
  "category": "Others"
 },
 {
  "nameEn": "Blood on the Wind",
  "types": [
   "Bozja"
  ],
  "category": "Others"
 },
 {
  "nameEn": "Wind on the Plains",
  "types": [
   "Bozja"
  ],
  "category": "Others"
 },
 {
  "nameEn": "Freefall",
  "types": [
   "Skybuilders"
  ],
  "category": "Trials"
 },
 {
  "nameEn": "The Heavens' Ward",
  "types": [
   "Skybuilders"
  ],
  "category": "Quests"
 },
 {
  "nameEn": "Eternal Wind (Shadowbringers)",
  "types": [
   "Crafting"
  ],
  "category": "Quests"
 },
 {
  "nameEn": "To the Edge",
  "types": [
   "Crafting"
  ],
  "category": "Trials"
 },
 {
  "nameEn": "Watts's Anvil",
  "types": [
   "Tribal"
  ],
  "category": "Locales II"
 },
 {
  "nameEn": "Torn from the Heavens／The Dark Colossus Destroys All (Medley Version)",
  "types": [
   "Raid"
  ],
  "category": "Raids II"
 },
 {
  "nameEn": "End of the Unknown",
  "types": [
   "Raid"
  ],
  "category": "Raids II"
 },
 {
  "nameEn": "Grandma (Destruction)",
  "types": [
   "Raid"
  ],
  "category": "Raids II"
 },
 {
  "nameEn": "Fortress of Lies",
  "types": [
   "Raid"
  ],
  "category": "Raids II"
 },
 {
  "nameEn": "Amusement Park",
  "types": [
   "Quest"
  ],
  "category": "Raids II"
 },
 {
  "nameEn": "Broken Heart",
  "types": [
   "Quest"
  ],
  "category": "Raids II"
 },
 {
  "nameEn": "Where All Roads Lead",
  "types": [
   "Dungeon",
   "Deep Dungeon"
  ],
  "category": "Dungeons II"
 },
 {
  "nameEn": "A Tonberry's Tears",
  "types": [
   "Dungeon"
  ],
  "category": "Dungeons I"
 },
 {
  "nameEn": "Abomination",
  "types": [
   "Dungeon"
  ],
  "category": "Dungeons I"
 },
 {
  "nameEn": "Hard to Miss",
  "types": [
   "Voyages",
   "Deep Dungeon"
  ],
  "category": "Others"
 },
 {
  "nameEn": "I Am the Sea (Piano Collections)",
  "types": [
   "Premium"
  ],
  "category": "Online Store & Bonuses"
 },
 {
  "nameEn": "Wailers and Waterwheels (Piano Collections)",
  "types": [
   "Premium"
  ],
  "category": "Online Store & Bonuses"
 },
 {
  "nameEn": "A New Hope (Piano Collections)",
  "types": [
   "Premium"
  ],
  "category": "Online Store & Bonuses"
 },
 {
  "nameEn": "Fealty",
  "types": [
   "Skybuilders"
  ],
  "category": "Locales I"
 },
 {
  "nameEn": "Paradise Found",
  "types": [
   "Skybuilders"
  ],
  "category": "Locales I"
 },
 {
  "nameEn": "Order Yet Undeciphered",
  "types": [
   "Skybuilders"
  ],
  "category": "Locales I"
 },
 {
  "nameEn": "The Mendicant's Relish",
  "types": [
   "Skybuilders"
  ],
  "category": "Others"
 },
 {
  "nameEn": "Stone and Steel",
  "types": [
   "Skybuilders"
  ],
  "category": "Quests"
 },
 {
  "nameEn": "Vamo' alla Flamenco (Shadowbringers)",
  "types": [
   "Gold Saucer"
  ],
  "category": "Quests"
 },
 {
  "nameEn": "Ultima (The Primals)",
  "types": [
   "Crafting"
  ],
  "category": "Trials"
 },
 {
  "nameEn": "Bedlam's Brink",
  "types": [
   "FATE"
  ],
  "category": "Quests"
 },
 {
  "nameEn": "On Our Fates Alight",
  "types": [
   "Treasure Hunt",
   "Deep Dungeon"
  ],
  "category": "Others"
 },
 {
  "nameEn": "No Greater Sorrow",
  "types": [
   "FATE"
  ],
  "category": "Locales II"
 },
 {
  "nameEn": "A Reason to Live",
  "types": [
   "FATE"
  ],
  "category": "Locales II"
 },
 {
  "nameEn": "Hopl's Dropple",
  "types": [
   "Tribal"
  ],
  "category": "Locales II"
 },
 {
  "nameEn": "Return to Oblivion",
  "types": [
   "Raid"
  ],
  "category": "Raids II"
 },
 {
  "nameEn": "Primal Angel",
  "types": [
   "Raid"
  ],
  "category": "Raids II"
 },
 {
  "nameEn": "Twice Stricken",
  "types": [
   "Raid"
  ],
  "category": "Raids II"
 },
 {
  "nameEn": "Floundering in the Depths",
  "types": [
   "Dungeon",
   "Deep Dungeon"
  ],
  "category": "Dungeons II"
 },
 {
  "nameEn": "Blue Fields (Shadowbringers)",
  "types": [
   "Quest"
  ],
  "category": "Raids II"
 },
 {
  "nameEn": "Crumbling Lies (Front)",
  "types": [
   "Quest"
  ],
  "category": "Raids II"
 },
 {
  "nameEn": "The Darkhold",
  "types": [
   "Dungeon"
  ],
  "category": "Dungeons I"
 },
 {
  "nameEn": "The Maiden's Lament",
  "types": [
   "Dungeon"
  ],
  "category": "Dungeons I"
 },
 {
  "nameEn": "Imperium",
  "types": [
   "Quest",
   "Hunts"
  ],
  "category": "Others"
 },
 {
  "nameEn": "Nail of the Heavens",
  "types": [
   "Quest",
   "Hunts"
  ],
  "category": "Others"
 },
 {
  "nameEn": "A Fine Air Forbiddeth",
  "types": [
   "PvP"
  ],
  "category": "Others"
 },
 {
  "nameEn": "A Fierce Air Forceth",
  "types": [
   "PvP"
  ],
  "category": "Others"
 },
 {
  "nameEn": "Safety in Numbers",
  "types": [
   "Skybuilders"
  ],
  "category": "Locales I"
 },
 {
  "nameEn": "Invincible",
  "types": [
   "Crafting"
  ],
  "category": "Trials"
 },
 {
  "nameEn": "The Garden's Gates",
  "types": [
   "Tribal"
  ],
  "category": "Locales II"
 },
 {
  "nameEn": "Neath Dark Waters",
  "types": [
   "FATE"
  ],
  "category": "Locales II"
 },
 {
  "nameEn": "A Hopeless Race",
  "types": [
   "FATE"
  ],
  "category": "Locales II"
 },
 {
  "nameEn": "The Faerie Ring",
  "types": [
   "FATE"
  ],
  "category": "Locales II"
 },
 {
  "nameEn": "Sands of Blood",
  "types": [
   "FATE"
  ],
  "category": "Locales II"
 },
 {
  "nameEn": "The Quick Way",
  "types": [
   "FATE"
  ],
  "category": "Locales II"
 },
 {
  "nameEn": "Unchanging, Everchanging",
  "types": [
   "FATE"
  ],
  "category": "Locales II"
 },
 {
  "nameEn": "Masquerade",
  "types": [
   "FATE"
  ],
  "category": "Locales II"
 },
 {
  "nameEn": "Knowledge Never Sleeps",
  "types": [
   "FATE"
  ],
  "category": "Locales II"
 },
 {
  "nameEn": "The Grand Cosmos",
  "types": [
   "Dungeon",
   "Deep Dungeon"
  ],
  "category": "Dungeons II"
 },
 {
  "nameEn": "Weight of the World (Prelude Version)",
  "types": [
   "Raid"
  ],
  "category": "Raids II"
 },
 {
  "nameEn": "Bipolar Nightmare",
  "types": [
   "Raid"
  ],
  "category": "Raids II"
 },
 {
  "nameEn": "Song of the Ancients (Atonement)",
  "types": [
   "Raid"
  ],
  "category": "Raids II"
 },
 {
  "nameEn": "Alien Manifestation",
  "types": [
   "Raid"
  ],
  "category": "Raids II"
 },
 {
  "nameEn": "Voice of no Return (Guitar)",
  "types": [
   "Quest"
  ],
  "category": "Raids II"
 },
 {
  "nameEn": "Pain in Pleasure",
  "types": [
   "Quest"
  ],
  "category": "Locales II"
 },
 {
  "nameEn": "City Ruins (Rays of Light)",
  "types": [
   "Raid"
  ],
  "category": "Raids II"
 },
 {
  "nameEn": "Significance (Nothing)",
  "types": [
   "Quest"
  ],
  "category": "Raids II"
 },
 {
  "nameEn": "The Worm's Tail (Orchestral Version)",
  "types": [
   "Premium"
  ],
  "category": "Online Store & Bonuses"
 },
 {
  "nameEn": "Tsukuyomi's Pain (Orchestral Version)",
  "types": [
   "Premium"
  ],
  "category": "Online Store & Bonuses"
 },
 {
  "nameEn": "Starlight de Chocobo",
  "types": [
   "Event",
   "Premium"
  ],
  "category": "Seasonal"
 },
 {
  "nameEn": "Insatiable",
  "types": [
   "Treasure Hunt"
  ],
  "category": "Dungeons II"
 },
 {
  "nameEn": "Landslide",
  "types": [
   "Raid"
  ],
  "category": "Raids II"
 },
 {
  "nameEn": "Blinding Indigo",
  "types": [
   "Raid"
  ],
  "category": "Raids II"
 },
 {
  "nameEn": "Force Your Way (Shadowbringers)",
  "types": [
   "Raid"
  ],
  "category": "Raids II"
 },
 {
  "nameEn": "Alienus",
  "types": [
   "Dungeon"
  ],
  "category": "Dungeons I"
 },
 {
  "nameEn": "Tomorrow and Tomorrow",
  "types": [
   "Quest"
  ],
  "category": "Quests"
 },
 {
  "nameEn": "Shadowbringers",
  "types": [
   "Quest"
  ],
  "category": "Quests"
 },
 {
  "nameEn": "Insanity",
  "types": [
   "Crafting"
  ],
  "category": "Trials"
 },
 {
  "nameEn": "What Angel Wakes Me",
  "types": [
   "Crafting",
   "Deep Dungeon"
  ],
  "category": "Trials"
 },
 {
  "nameEn": "Rencounter",
  "types": [
   "Hunts"
  ],
  "category": "Locales II"
 },
 {
  "nameEn": "Fury",
  "types": [
   "Dungeon"
  ],
  "category": "Dungeons I"
 },
 {
  "nameEn": "Full Fathom Five",
  "types": [
   "FATE"
  ],
  "category": "Locales II"
 },
 {
  "nameEn": "Shadows Withal",
  "types": [
   "Dungeon",
   "Deep Dungeon"
  ],
  "category": "Dungeons II"
 },
 {
  "nameEn": "Civilizations",
  "types": [
   "FATE"
  ],
  "category": "Locales II"
 },
 {
  "nameEn": "A Long Fall",
  "types": [
   "Dungeon",
   "Deep Dungeon"
  ],
  "category": "Dungeons II"
 },
 {
  "nameEn": "Fierce and Free",
  "types": [
   "FATE"
  ],
  "category": "Locales II"
 },
 {
  "nameEn": "Mortal Instants",
  "types": [
   "Dungeon",
   "Deep Dungeon"
  ],
  "category": "Dungeons II"
 },
 {
  "nameEn": "Sands of Amber",
  "types": [
   "FATE"
  ],
  "category": "Locales II"
 },
 {
  "nameEn": "In the Belly of the Beast",
  "types": [
   "Dungeon",
   "Deep Dungeon"
  ],
  "category": "Dungeons II"
 },
 {
  "nameEn": "A World Divided",
  "types": [
   "FATE"
  ],
  "category": "Locales II"
 },
 {
  "nameEn": "Deep Down",
  "types": [
   "Dungeon",
   "Deep Dungeon"
  ],
  "category": "Dungeons II"
 },
 {
  "nameEn": "The Source",
  "types": [
   "FATE"
  ],
  "category": "Locales II"
 },
 {
  "nameEn": "Unwound",
  "types": [
   "Dungeon",
   "Deep Dungeon"
  ],
  "category": "Dungeons II"
 },
 {
  "nameEn": "Indulgence",
  "types": [
   "FATE"
  ],
  "category": "Locales II"
 },
 {
  "nameEn": "Figments",
  "types": [
   "Dungeon",
   "Deep Dungeon"
  ],
  "category": "Dungeons II"
 },
 {
  "nameEn": "The Dark Which Illuminates the World",
  "types": [
   "FATE"
  ],
  "category": "Locales II"
 },
 {
  "nameEn": "To Fire and Sword",
  "types": [
   "Dungeon",
   "Deep Dungeon"
  ],
  "category": "Dungeons II"
 },
 {
  "nameEn": "Turmoil",
  "types": [
   "Eureka"
  ],
  "category": "Others"
 },
 {
  "nameEn": "Onslaught",
  "types": [
   "Eureka"
  ],
  "category": "Others"
 },
 {
  "nameEn": "Gates of Paradise - The Garden of Ru'Hmet",
  "types": [
   "Eureka"
  ],
  "category": "Others"
 },
 {
  "nameEn": "eScape (Journeys Version)",
  "types": [
   "Premium"
  ],
  "category": "Online Store & Bonuses"
 },
 {
  "nameEn": "The Worm's Tail (Journeys Version)",
  "types": [
   "Premium"
  ],
  "category": "Online Store & Bonuses"
 },
 {
  "nameEn": "A Quick Pit Stop",
  "types": [
   "Event"
  ],
  "category": "Seasonal"
 },
 {
  "nameEn": "Apocalypsis Noctis",
  "types": [
   "Event"
  ],
  "category": "Seasonal"
 },
 {
  "nameEn": "Veiled in Black",
  "types": [
   "Event"
  ],
  "category": "Seasonal"
 },
 {
  "nameEn": "Relax and Reflect",
  "types": [
   "Event"
  ],
  "category": "Seasonal"
 },
 {
  "nameEn": "Valse di Fantastica",
  "types": [
   "Event"
  ],
  "category": "Seasonal"
 },
 {
  "nameEn": "Hammerhead",
  "types": [
   "Event"
  ],
  "category": "Seasonal"
 },
 {
  "nameEn": "Harmony",
  "types": [
   "Crafting"
  ],
  "category": "Locales I"
 },
 {
  "nameEn": "A Pall Most Murderous",
  "types": [
   "Dungeon",
   "Deep Dungeon"
  ],
  "category": "Dungeons I"
 },
 {
  "nameEn": "Old Wounds",
  "types": [
   "Gathering"
  ],
  "category": "Locales I"
 },
 {
  "nameEn": "The Stone Remembers",
  "types": [
   "Gathering"
  ],
  "category": "Locales I"
 },
 {
  "nameEn": "Hope Forgotten",
  "types": [
   "Gathering"
  ],
  "category": "Locales I"
 },
 {
  "nameEn": "Afterglow",
  "types": [
   "Crafting"
  ],
  "category": "Locales I"
 },
 {
  "nameEn": "Ultima's Perfection",
  "types": [
   "Raid"
  ],
  "category": "Raids I"
 },
 {
  "nameEn": "A Man Consumed",
  "types": [
   "Raid"
  ],
  "category": "Raids I"
 },
 {
  "nameEn": "Antipyretic",
  "types": [
   "Raid"
  ],
  "category": "Raids I"
 },
 {
  "nameEn": "Pressure (No. 1)",
  "types": [
   "Raid"
  ],
  "category": "Raids I"
 },
 {
  "nameEn": "Under the Stars",
  "types": [
   "Raid"
  ],
  "category": "Raids I"
 },
 {
  "nameEn": "Alma's Theme",
  "types": [
   "Quest"
  ],
  "category": "Raids I"
 },
 {
  "nameEn": "Staff Credits",
  "types": [
   "Quest"
  ],
  "category": "Raids I"
 },
 {
  "nameEn": "From the Dragon's Wake",
  "types": [
   "Crafting"
  ],
  "category": "Trials"
 },
 {
  "nameEn": "Rise of Heroes (Chiptune Version)",
  "types": [
   "Gold Saucer"
  ],
  "category": "Others"
 },
 {
  "nameEn": "Doman Distractions",
  "types": [
   "Achievement"
  ],
  "category": "Others"
 },
 {
  "nameEn": "Game Theory",
  "types": [
   "Gold Saucer"
  ],
  "category": "Others"
 },
 {
  "nameEn": "Beyond Redemption",
  "types": [
   "Achievement"
  ],
  "category": "Raids I"
 },
 {
  "nameEn": "Moebius (Orchestral Version)",
  "types": [
   "Premium"
  ],
  "category": "Online Store & Bonuses"
 },
 {
  "nameEn": "Painted Foothills (Orchestral Version)",
  "types": [
   "Premium"
  ],
  "category": "Online Store & Bonuses"
 },
 {
  "nameEn": "Oblivion (GUNN Vocals)",
  "types": [
   "Premium"
  ],
  "category": "Online Store & Bonuses"
 },
 {
  "nameEn": "Rise (The Primals)",
  "types": [
   "Premium"
  ],
  "category": "Online Store & Bonuses"
 },
 {
  "nameEn": "The Worm's Tail (Chiptune Version)",
  "types": [
   "Premium"
  ],
  "category": "Online Store & Bonuses"
 },
 {
  "nameEn": "Wayward Daughter (Chiptune Version)",
  "types": [
   "Premium"
  ],
  "category": "Online Store & Bonuses"
 },
 {
  "nameEn": "Cradle",
  "types": [
   "Purchase"
  ],
  "category": "Locales I"
 },
 {
  "nameEn": "From Mud",
  "types": [
   "Dungeon",
   "Deep Dungeon"
  ],
  "category": "Dungeons I"
 },
 {
  "nameEn": "A Land Long Dead",
  "types": [
   "Dungeon",
   "Deep Dungeon"
  ],
  "category": "Dungeons I"
 },
 {
  "nameEn": "From the Heavens",
  "types": [
   "Raid"
  ],
  "category": "Raids I"
 },
 {
  "nameEn": "Heartless",
  "types": [
   "Raid"
  ],
  "category": "Raids I"
 },
 {
  "nameEn": "eScape",
  "types": [
   "Raid"
  ],
  "category": "Raids I"
 },
 {
  "nameEn": "Primogenitor",
  "types": [
   "Raid"
  ],
  "category": "Raids I"
 },
 {
  "nameEn": "Battle",
  "types": [
   "Raid"
  ],
  "category": "Raids I"
 },
 {
  "nameEn": "Dancing Mad - Movement IV",
  "types": [
   "Raid"
  ],
  "category": "Raids I"
 },
 {
  "nameEn": "Dancing Mad - Movement III",
  "types": [
   "Raid"
  ],
  "category": "Raids I"
 },
 {
  "nameEn": "Dancing Mad - Movement II",
  "types": [
   "Raid"
  ],
  "category": "Raids I"
 },
 {
  "nameEn": "Dancing Mad - Movement I",
  "types": [
   "Raid"
  ],
  "category": "Raids I"
 },
 {
  "nameEn": "A Battle Decisively",
  "types": [
   "Raid"
  ],
  "category": "Raids I"
 },
 {
  "nameEn": "Final, Not Final",
  "types": [
   "Raid"
  ],
  "category": "Raids I"
 },
 {
  "nameEn": "Decisions (Omega)",
  "types": [
   "Raid"
  ],
  "category": "Raids I"
 },
 {
  "nameEn": "Omega Squared",
  "types": [
   "Raid"
  ],
  "category": "Raids I"
 },
 {
  "nameEn": "Deltascape",
  "types": [
   "Quest"
  ],
  "category": "Raids I"
 },
 {
  "nameEn": "Upon the Rocks",
  "types": [
   "Dungeon",
   "Skybuilders"
  ],
  "category": "Dungeons I"
 },
 {
  "nameEn": "Ending",
  "types": [
   "Quest"
  ],
  "category": "Quests"
 },
 {
  "nameEn": "A Dream in Flight",
  "types": [
   "Quest"
  ],
  "category": "Quests"
 },
 {
  "nameEn": "Sunrise",
  "types": [
   "Crafting"
  ],
  "category": "Trials"
 },
 {
  "nameEn": "Tricksome",
  "types": [
   "Dungeon",
   "Skybuilders"
  ],
  "category": "Dungeons I"
 },
 {
  "nameEn": "Beneath Bloodied Banners",
  "types": [
   "Dungeon"
  ],
  "category": "Dungeons I"
 },
 {
  "nameEn": "Ominous Prognisticks (Orchestral Version)",
  "types": [
   "Premium"
  ],
  "category": "Online Store & Bonuses"
 },
 {
  "nameEn": "Calamity Unbound (Orchestral Version)",
  "types": [
   "Premium"
  ],
  "category": "Online Store & Bonuses"
 },
 {
  "nameEn": "Serenity (Orchestral Version)",
  "types": [
   "Premium"
  ],
  "category": "Online Store & Bonuses"
 },
 {
  "nameEn": "Starlight, Starbright",
  "types": [
   "Event",
   "Premium"
  ],
  "category": "Seasonal"
 },
 {
  "nameEn": "Proof of a Hero - Monster Hunter: World Version",
  "types": [
   "Trial"
  ],
  "category": "Trials"
 },
 {
  "nameEn": "Savage of the Ancient Forest",
  "types": [
   "Trial"
  ],
  "category": "Trials"
 },
 {
  "nameEn": "Cornerstone of the New World - Astera",
  "types": [
   "Trial"
  ],
  "category": "Others"
 },
 {
  "nameEn": "Parting Ways",
  "types": [
   "Deep Dungeon"
  ],
  "category": "Quests"
 },
 {
  "nameEn": "Far East of Eorzea",
  "types": [
   "Deep Dungeon"
  ],
  "category": "Quests"
 },
 {
  "nameEn": "Revolutions",
  "types": [
   "Event",
   "Premium"
  ],
  "category": "Seasonal"
 },
 {
  "nameEn": "Seven Hundred Seventy-Seven Whiskers",
  "types": [
   "Tribal"
  ],
  "category": "Locales I"
 },
 {
  "nameEn": "Earth, Wind, and Water",
  "types": [
   "Dungeon",
   "Deep Dungeon"
  ],
  "category": "Dungeons I"
 },
 {
  "nameEn": "Gates of the Moon",
  "types": [
   "Dungeon"
  ],
  "category": "Dungeons I"
 },
 {
  "nameEn": "The Ancient City",
  "types": [
   "Dungeon"
  ],
  "category": "Dungeons I"
 },
 {
  "nameEn": "Flash of Steel",
  "types": [
   "Raid"
  ],
  "category": "Raids I"
 },
 {
  "nameEn": "Apoplexy",
  "types": [
   "Raid"
  ],
  "category": "Raids I"
 },
 {
  "nameEn": "Black and White",
  "types": [
   "Crafting"
  ],
  "category": "Locales I"
 },
 {
  "nameEn": "The Mystery of Giruvegan",
  "types": [
   "Raid"
  ],
  "category": "Raids I"
 },
 {
  "nameEn": "Victory or Death",
  "types": [
   "Purchase"
  ],
  "category": "Quests"
 },
 {
  "nameEn": "A Chapel",
  "types": [
   "Quest"
  ],
  "category": "Raids I"
 },
 {
  "nameEn": "World Map",
  "types": [
   "Quest"
  ],
  "category": "Raids I"
 },
 {
  "nameEn": "Wayward Daughter",
  "types": [
   "Crafting"
  ],
  "category": "Trials"
 },
 {
  "nameEn": "Nightbloom",
  "types": [
   "Crafting"
  ],
  "category": "Trials"
 },
 {
  "nameEn": "Ambient Abyss",
  "types": [
   "Crafting"
  ],
  "category": "Ambient"
 },
 {
  "nameEn": "Ambient Wind Chime",
  "types": [
   "Purchase"
  ],
  "category": "Ambient"
 },
 {
  "nameEn": "Oblivion (Orchestral Version)",
  "types": [
   "Premium"
  ],
  "category": "Online Store & Bonuses"
 },
 {
  "nameEn": "Revenge Twofold (Orchestral Version)",
  "types": [
   "Premium"
  ],
  "category": "Online Store & Bonuses"
 },
 {
  "nameEn": "Rise of the White Raven (Orchestral Version)",
  "types": [
   "Premium"
  ],
  "category": "Online Store & Bonuses"
 },
 {
  "nameEn": "No Quarter",
  "types": [
   "Eureka"
  ],
  "category": "Others"
 },
 {
  "nameEn": "Wicked Winds Whisper",
  "types": [
   "Eureka"
  ],
  "category": "Others"
 },
 {
  "nameEn": "Triumph",
  "types": [
   "Gold Saucer"
  ],
  "category": "Dungeons I"
 },
 {
  "nameEn": "Keepers of the Lock",
  "types": [
   "Tribal"
  ],
  "category": "Locales I"
 },
 {
  "nameEn": "He Rises Above",
  "types": [
   "Purchase"
  ],
  "category": "Locales I"
 },
 {
  "nameEn": "A Mother's Pride",
  "types": [
   "Treasure Hunt"
  ],
  "category": "Locales I"
 },
 {
  "nameEn": "Unbreakable (Duality)",
  "types": [
   "Dungeon",
   "Deep Dungeon"
  ],
  "category": "Dungeons I"
 },
 {
  "nameEn": "Westward Tide",
  "types": [
   "Purchase"
  ],
  "category": "Locales I"
 },
 {
  "nameEn": "Down Where Daemons Dwell",
  "types": [
   "Dungeon",
   "Deep Dungeon"
  ],
  "category": "Dungeons I"
 },
 {
  "nameEn": "Crimson Sunset",
  "types": [
   "Treasure Hunt"
  ],
  "category": "Locales I"
 },
 {
  "nameEn": "Their Deadly Mission",
  "types": [
   "Dungeon",
   "Deep Dungeon"
  ],
  "category": "Dungeons I"
 },
 {
  "nameEn": "Liberty or Death",
  "types": [
   "Dungeon"
  ],
  "category": "Dungeons I"
 },
 {
  "nameEn": "Revenge Twofold",
  "types": [
   "Gold Saucer"
  ],
  "category": "Dungeons I"
 },
 {
  "nameEn": "Iroha",
  "types": [
   "Quest"
  ],
  "category": "Quests"
 },
 {
  "nameEn": "Cyan's Theme",
  "types": [
   "Quest"
  ],
  "category": "Quests"
 },
 {
  "nameEn": "Amatsu Kaze",
  "types": [
   "Crafting"
  ],
  "category": "Trials"
 },
 {
  "nameEn": "Answer on High",
  "types": [
   "Crafting"
  ],
  "category": "Trials"
 },
 {
  "nameEn": "Prelude - Long March Home",
  "types": [
   "Achievement"
  ],
  "category": "Quests"
 },
 {
  "nameEn": "Fragments of Forever",
  "types": [
   "Purchase"
  ],
  "category": "Quests"
 },
 {
  "nameEn": "Chapel Bell",
  "types": [
   "Purchase",
   "Deep Dungeon"
  ],
  "category": "Ambient"
 },
 {
  "nameEn": "Temple Bell",
  "types": [
   "Purchase"
  ],
  "category": "Ambient"
 },
 {
  "nameEn": "Bustling Boulevard",
  "types": [
   "Purchase"
  ],
  "category": "Ambient"
 },
 {
  "nameEn": "Rival Wings",
  "types": [
   "PvP"
  ],
  "category": "Others"
 },
 {
  "nameEn": "Babbling Brook",
  "types": [
   "Purchase",
   "Deep Dungeon"
  ],
  "category": "Ambient"
 },
 {
  "nameEn": "Shattered",
  "types": [
   "Raid"
  ],
  "category": "Raids I"
 },
 {
  "nameEn": "Daring Dalliances",
  "types": [
   "Purchase"
  ],
  "category": "Quests"
 },
 {
  "nameEn": "Siren Song",
  "types": [
   "Event",
   "Premium"
  ],
  "category": "Seasonal"
 },
 {
  "nameEn": "Birds of Prey",
  "types": [
   "PvP"
  ],
  "category": "Others"
 },
 {
  "nameEn": "Indomitable",
  "types": [
   "Tribal"
  ],
  "category": "Locales I"
 },
 {
  "nameEn": "Far From Home",
  "types": [
   "Dungeon",
   "Deep Dungeon"
  ],
  "category": "Dungeons I"
 },
 {
  "nameEn": "Deception",
  "types": [
   "Dungeon"
  ],
  "category": "Dungeons I"
 },
 {
  "nameEn": "A Father's Pride",
  "types": [
   "Treasure Hunt"
  ],
  "category": "Locales I"
 },
 {
  "nameEn": "Most Unworthy",
  "types": [
   "Dungeon"
  ],
  "category": "Dungeons I"
 },
 {
  "nameEn": "The Open Box",
  "types": [
   "Dungeon"
  ],
  "category": "Dungeons I"
 },
 {
  "nameEn": "Crimson Sunrise",
  "types": [
   "Treasure Hunt"
  ],
  "category": "Locales I"
 },
 {
  "nameEn": "Songs of Salt and Suffering",
  "types": [
   "Gathering"
  ],
  "category": "Locales I"
 },
 {
  "nameEn": "On High",
  "types": [
   "Crafting"
  ],
  "category": "Locales I"
 },
 {
  "nameEn": "Impact",
  "types": [
   "Purchase"
  ],
  "category": "Locales I"
 },
 {
  "nameEn": "Background Story",
  "types": [
   "Quest"
  ],
  "category": "Raids I"
 },
 {
  "nameEn": "Protagonist's Theme",
  "types": [
   "Quest"
  ],
  "category": "Raids I"
 },
 {
  "nameEn": "Ultima's Transformation",
  "types": [
   "Raid"
  ],
  "category": "Raids I"
 },
 {
  "nameEn": "Precipitous Combat",
  "types": [
   "Raid"
  ],
  "category": "Raids I"
 },
 {
  "nameEn": "Trisection",
  "types": [
   "Raid"
  ],
  "category": "Raids I"
 },
 {
  "nameEn": "The Measure of Our Reach",
  "types": [
   "Quest"
  ],
  "category": "Quests"
 },
 {
  "nameEn": "The Measure of His Reach",
  "types": [
   "Quest"
  ],
  "category": "Quests"
 },
 {
  "nameEn": "The Worm's Tail",
  "types": [
   "Crafting"
  ],
  "category": "Trials"
 },
 {
  "nameEn": "The Worm's Head",
  "types": [
   "Crafting"
  ],
  "category": "Trials"
 },
 {
  "nameEn": "Ambient Kitchen",
  "types": [
   "Purchase"
  ],
  "category": "Ambient"
 },
 {
  "nameEn": "Ambient Bonfire",
  "types": [
   "Purchase"
  ],
  "category": "Ambient"
 },
 {
  "nameEn": "Ambient Insects",
  "types": [
   "Purchase"
  ],
  "category": "Ambient"
 },
 {
  "nameEn": "Starlit Gateway",
  "types": [
   "Event",
   "Premium"
  ],
  "category": "Seasonal"
 },
 {
  "nameEn": "Heroes (Orchestral Version)",
  "types": [
   "Premium"
  ],
  "category": "Online Store & Bonuses"
 },
 {
  "nameEn": "Ultima (Orchestral Version)",
  "types": [
   "Premium"
  ],
  "category": "Online Store & Bonuses"
 },
 {
  "nameEn": "The Twin Faces of Fate - The Theme of Ul'dah",
  "types": [
   "Treasure Hunt",
   "Skybuilders"
  ],
  "category": "Locales I"
 },
 {
  "nameEn": "Born of the Boughs - The Theme of Gridania",
  "types": [
   "Treasure Hunt",
   "Skybuilders"
  ],
  "category": "Locales I"
 },
 {
  "nameEn": "Navigator's Glory - The Theme of Limsa Lominsa",
  "types": [
   "Treasure Hunt",
   "Skybuilders"
  ],
  "category": "Locales I"
 },
 {
  "nameEn": "Stormblood",
  "types": [
   "Event",
   "Premium"
  ],
  "category": "Seasonal"
 },
 {
  "nameEn": "Answers - Reprise",
  "types": [
   "Event",
   "Premium"
  ],
  "category": "Seasonal"
 },
 {
  "nameEn": "Hyper Rainbow Z",
  "types": [
   "Event",
   "Premium"
  ],
  "category": "Seasonal"
 },
 {
  "nameEn": "Drowning in the Horizon",
  "types": [
   "Hunts"
  ],
  "category": "Locales I"
 },
 {
  "nameEn": "Liquid Flame",
  "types": [
   "FATE"
  ],
  "category": "Locales I"
 },
 {
  "nameEn": "Beyond the Wall",
  "types": [
   "FATE"
  ],
  "category": "Locales I"
 },
 {
  "nameEn": "Bibliophobia",
  "types": [
   "Dungeon",
   "Deep Dungeon"
  ],
  "category": "Dungeons I"
 },
 {
  "nameEn": "The Silent Regard of Stars",
  "types": [
   "Crafting"
  ],
  "category": "Locales I"
 },
 {
  "nameEn": "Poison Ivy",
  "types": [
   "Dungeon"
  ],
  "category": "Dungeons I"
 },
 {
  "nameEn": "Skylords",
  "types": [
   "Crafting"
  ],
  "category": "Locales I"
 },
 {
  "nameEn": "The Edge",
  "types": [
   "Purchase"
  ],
  "category": "Locales I"
 },
 {
  "nameEn": "Beauty's Wicked Wiles",
  "types": [
   "Crafting"
  ],
  "category": "Trials"
 },
 {
  "nameEn": "Revelation",
  "types": [
   "Crafting"
  ],
  "category": "Trials"
 },
 {
  "nameEn": "Ambient Cricketsong",
  "types": [
   "Purchase"
  ],
  "category": "Ambient"
 },
 {
  "nameEn": "Ambient Rainfall",
  "types": [
   "Purchase"
  ],
  "category": "Ambient"
 },
 {
  "nameEn": "Ambient Waves",
  "types": [
   "Purchase",
   "Deep Dungeon"
  ],
  "category": "Ambient"
 },
 {
  "nameEn": "Ambient Birdsong",
  "types": [
   "Purchase"
  ],
  "category": "Ambient"
 },
 {
  "nameEn": "He Who Continues the Attack",
  "types": [
   "Quest"
  ],
  "category": "Quests"
 },
 {
  "nameEn": "Imperial Will",
  "types": [
   "Quest"
  ],
  "category": "Quests"
 },
 {
  "nameEn": "Steel Reason",
  "types": [
   "Quest"
  ],
  "category": "Quests"
 },
 {
  "nameEn": "Jewel",
  "types": [
   "Skybuilders"
  ],
  "category": "Others"
 },
 {
  "nameEn": "Quicksand",
  "types": [
   "Quest"
  ],
  "category": "Dungeons I"
 },
 {
  "nameEn": "Another Brick",
  "types": [
   "Quest"
  ],
  "category": "Dungeons I"
 },
 {
  "nameEn": "Thicker than a Knife's Blade",
  "types": [
   "Hunts"
  ],
  "category": "Locales I"
 },
 {
  "nameEn": "Piece of Mind",
  "types": [
   "Tribal"
  ],
  "category": "Locales I"
 },
 {
  "nameEn": "Hallowed Halls",
  "types": [
   "Dungeon"
  ],
  "category": "Dungeons I"
 },
 {
  "nameEn": "Moebius",
  "types": [
   "Raid"
  ],
  "category": "Raids I"
 },
 {
  "nameEn": "Saltswept",
  "types": [
   "Purchase"
  ],
  "category": "Locales I"
 },
 {
  "nameEn": "Fleeting Rays",
  "types": [
   "FATE"
  ],
  "category": "Locales I"
 },
 {
  "nameEn": "Frontiers Within",
  "types": [
   "Purchase"
  ],
  "category": "Locales I"
 },
 {
  "nameEn": "Infinity",
  "types": [
   "Crafting"
  ],
  "category": "Trials"
 },
 {
  "nameEn": "Unbending Steel",
  "types": [
   "Crafting"
  ],
  "category": "Trials"
 },
 {
  "nameEn": "Shadow of the Body",
  "types": [
   "Quest"
  ],
  "category": "Raids I"
 },
 {
  "nameEn": "The Hand that Gives the Rose",
  "types": [
   "Crafting"
  ],
  "category": "Trials"
 },
 {
  "nameEn": "Promises",
  "types": [
   "Quest"
  ],
  "category": "Raids I"
 },
 {
  "nameEn": "Woe that Is Madness",
  "types": [
   "Crafting"
  ],
  "category": "Trials"
 },
 {
  "nameEn": "Flibbertigibbet",
  "types": [
   "Tribal"
  ],
  "category": "Locales I"
 },
 {
  "nameEn": "A Thousand Faces",
  "types": [
   "Purchase"
  ],
  "category": "Raids I"
 },
 {
  "nameEn": "Limitless Blue",
  "types": [
   "Crafting"
  ],
  "category": "Trials"
 },
 {
  "nameEn": "Teardrops in the Rain",
  "types": [
   "Purchase"
  ],
  "category": "Raids I"
 },
 {
  "nameEn": "The Corpse Hall",
  "types": [
   "Crafting"
  ],
  "category": "Trials"
 },
 {
  "nameEn": "Six Fulms Under",
  "types": [
   "Purchase"
  ],
  "category": "Raids I"
 },
 {
  "nameEn": "Aetherosphere",
  "types": [
   "Purchase"
  ],
  "category": "Raids I"
 },
 {
  "nameEn": "Breaking Boundaries",
  "types": [
   "Treasure Hunt"
  ],
  "category": "Quests"
 },
 {
  "nameEn": "Tempest",
  "types": [
   "Gold Saucer"
  ],
  "category": "Raids I"
 },
 {
  "nameEn": "Spiral",
  "types": [
   "Gold Saucer"
  ],
  "category": "Raids I"
 },
 {
  "nameEn": "Canticle",
  "types": [
   "Purchase"
  ],
  "category": "Quests"
 },
 {
  "nameEn": "Forever Lost",
  "types": [
   "Quest"
  ],
  "category": "Quests"
 },
 {
  "nameEn": "The Kiss",
  "types": [
   "Event",
   "Premium"
  ],
  "category": "Seasonal"
 },
 {
  "nameEn": "Notice of Death",
  "types": [
   "Deep Dungeon"
  ],
  "category": "Dungeons I"
 },
 {
  "nameEn": "Blasphemous Experiment",
  "types": [
   "Deep Dungeon"
  ],
  "category": "Dungeons I"
 },
 {
  "nameEn": "Fog of Phantom",
  "types": [
   "Deep Dungeon"
  ],
  "category": "Dungeons I"
 },
 {
  "nameEn": "Blackbosom",
  "types": [
   "Deep Dungeon"
  ],
  "category": "Dungeons I"
 },
 {
  "nameEn": "Unbending Steel (Duality)",
  "types": [
   "Premium"
  ],
  "category": "Online Store & Bonuses"
 },
 {
  "nameEn": "Borderless (Duality)",
  "types": [
   "Premium"
  ],
  "category": "Online Store & Bonuses"
 },
 {
  "nameEn": "Heavensturn",
  "types": [
   "Event",
   "Premium"
  ],
  "category": "Seasonal"
 },
 {
  "nameEn": "Starlight Celebration",
  "types": [
   "Event",
   "Premium"
  ],
  "category": "Seasonal"
 },
 {
  "nameEn": "Grounded",
  "types": [
   "Quest"
  ],
  "category": "Dungeons I"
 },
 {
  "nameEn": "Homestead",
  "types": [
   "Purchase"
  ],
  "category": "Locales I"
 },
 {
  "nameEn": "Coming Home",
  "types": [
   "Tribal"
  ],
  "category": "Locales I"
 },
 {
  "nameEn": "Close to the Heavens",
  "types": [
   "Crafting"
  ],
  "category": "Locales I"
 },
 {
  "nameEn": "Night in the Brume",
  "types": [
   "Purchase"
  ],
  "category": "Locales I"
 },
 {
  "nameEn": "Nobility Sleeps",
  "types": [
   "Purchase"
  ],
  "category": "Locales I"
 },
 {
  "nameEn": "Slumber Eternal",
  "types": [
   "Dungeon"
  ],
  "category": "Dungeons I"
 },
 {
  "nameEn": "Rise",
  "types": [
   "Quest"
  ],
  "category": "Raids I"
 },
 {
  "nameEn": "Exponential Entropy",
  "types": [
   "Quest"
  ],
  "category": "Raids I"
 },
 {
  "nameEn": "Metal - Brute Justice Mode",
  "types": [
   "Quest"
  ],
  "category": "Raids I"
 },
 {
  "nameEn": "Metal",
  "types": [
   "Quest"
  ],
  "category": "Raids I"
 },
 {
  "nameEn": "Locus",
  "types": [
   "Quest"
  ],
  "category": "Raids I"
 },
 {
  "nameEn": "Reflections",
  "types": [
   "Purchase"
  ],
  "category": "Locales I"
 },
 {
  "nameEn": "Sins of the Father, Sins of the Son",
  "types": [
   "Quest"
  ],
  "category": "Raids I"
 },
 {
  "nameEn": "Where the Heart Is",
  "types": [
   "Purchase"
  ],
  "category": "Locales I"
 },
 {
  "nameEn": "Behind Closed Doors",
  "types": [
   "Purchase"
  ],
  "category": "Locales I"
 },
 {
  "nameEn": "Silver Tears",
  "types": [
   "Dungeon"
  ],
  "category": "Dungeons I"
 },
 {
  "nameEn": "Smoulder",
  "types": [
   "Tribal"
  ],
  "category": "Locales I"
 },
 {
  "nameEn": "Equilibrium",
  "types": [
   "Crafting"
  ],
  "category": "Trials"
 },
 {
  "nameEn": "Battle Theme 1.x",
  "types": [
   "Gold Saucer"
  ],
  "category": "Quests"
 },
 {
  "nameEn": "Thunder Rolls",
  "types": [
   "Crafting"
  ],
  "category": "Trials"
 },
 {
  "nameEn": "Oblivion",
  "types": [
   "Crafting"
  ],
  "category": "Trials"
 },
 {
  "nameEn": "Unspoken",
  "types": [
   "Treasure Hunt"
  ],
  "category": "Locales I"
 },
 {
  "nameEn": "Footsteps in the Snow",
  "types": [
   "Crafting"
  ],
  "category": "Trials"
 },
 {
  "nameEn": "The Seventh Sun",
  "types": [
   "Achievement"
  ],
  "category": "Quests"
 },
 {
  "nameEn": "Calamity Unbound",
  "types": [
   "Treasure Hunt"
  ],
  "category": "Raids I"
 },
 {
  "nameEn": "Up at Dawn",
  "types": [
   "Event",
   "Premium"
  ],
  "category": "Seasonal"
 },
 {
  "nameEn": "All Saints' Wake",
  "types": [
   "Event",
   "Premium"
  ],
  "category": "Seasonal"
 },
 {
  "nameEn": "Ominous Prognisticks",
  "types": [
   "Purchase"
  ],
  "category": "Dungeons I"
 },
 {
  "nameEn": "Apologies",
  "types": [
   "Dungeon"
  ],
  "category": "Dungeons I"
 },
 {
  "nameEn": "Shelter",
  "types": [
   "Purchase"
  ],
  "category": "Locales I"
 },
 {
  "nameEn": "The Mushroomery",
  "types": [
   "Purchase"
  ],
  "category": "Locales I"
 },
 {
  "nameEn": "Unbreakable",
  "types": [
   "Dungeon"
  ],
  "category": "Dungeons I"
 },
 {
  "nameEn": "Ink Long Dry",
  "types": [
   "Dungeon",
   "Deep Dungeon"
  ],
  "category": "Dungeons I"
 },
 {
  "nameEn": "Missing Pages",
  "types": [
   "Crafting"
  ],
  "category": "Locales I"
 },
 {
  "nameEn": "Landlords",
  "types": [
   "Crafting"
  ],
  "category": "Locales I"
 },
 {
  "nameEn": "Against the Wind",
  "types": [
   "Crafting"
  ],
  "category": "Locales I"
 },
 {
  "nameEn": "Nobility Obliges",
  "types": [
   "Purchase"
  ],
  "category": "Locales I"
 },
 {
  "nameEn": "Engage",
  "types": [
   "Crafting"
  ],
  "category": "Quests"
 },
 {
  "nameEn": "Dragonsong",
  "types": [
   "Quest"
  ],
  "category": "Quests"
 },
 {
  "nameEn": "The Warrens",
  "types": [
   "Dungeon"
  ],
  "category": "Dungeons I"
 },
 {
  "nameEn": "Defender of the Realm",
  "types": [
   "Achievement"
  ],
  "category": "Quests"
 },
 {
  "nameEn": "Horizons Calling",
  "types": [
   "Dungeon",
   "Deep Dungeon"
  ],
  "category": "Dungeons I"
 },
 {
  "nameEn": "Twilight over Thanalan",
  "types": [
   "Treasure Hunt"
  ],
  "category": "Locales I"
 },
 {
  "nameEn": "Whisper of the Land",
  "types": [
   "Treasure Hunt"
  ],
  "category": "Locales I"
 },
 {
  "nameEn": "Battle to the Death - Heavensward",
  "types": [
   "Gold Saucer"
  ],
  "category": "Trials"
 },
 {
  "nameEn": "On Windy Meadows",
  "types": [
   "Treasure Hunt"
  ],
  "category": "Locales I"
 },
 {
  "nameEn": "Battle on the Big Bridge",
  "types": [
   "Crafting"
  ],
  "category": "Trials"
 },
 {
  "nameEn": "Revenge of the Horde",
  "types": [
   "Crafting"
  ],
  "category": "Trials"
 },
 {
  "nameEn": "Good King Moggle Mog XII",
  "types": [
   "Crafting"
  ],
  "category": "Trials"
 },
 {
  "nameEn": "Through the Maelstrom",
  "types": [
   "Crafting"
  ],
  "category": "Trials"
 },
 {
  "nameEn": "Wreck to the Seaman",
  "types": [
   "Crafting"
  ],
  "category": "Trials"
 },
 {
  "nameEn": "To the Sun",
  "types": [
   "Purchase"
  ],
  "category": "Locales I"
 },
 {
  "nameEn": "Serenity",
  "types": [
   "Purchase"
  ],
  "category": "Locales I"
 },
 {
  "nameEn": "On Westerly Winds",
  "types": [
   "Purchase"
  ],
  "category": "Locales I"
 },
 {
  "nameEn": "Sultana Dreaming",
  "types": [
   "Purchase"
  ],
  "category": "Locales I"
 },
 {
  "nameEn": "Dance of the Fireflies",
  "types": [
   "Purchase"
  ],
  "category": "Locales I"
 },
 {
  "nameEn": "A Sailor Never Sleeps",
  "types": [
   "Purchase"
  ],
  "category": "Locales I"
 },
 {
  "nameEn": "Heavensward",
  "types": [
   "Event",
   "Premium"
  ],
  "category": "Seasonal"
 },
 {
  "nameEn": "Moonfire Faire",
  "types": [
   "Event",
   "Premium"
  ],
  "category": "Seasonal"
 },
 {
  "nameEn": "Down the Up Staircase",
  "types": [
   "Crafting",
   "Deep Dungeon"
  ],
  "category": "Dungeons I"
 },
 {
  "nameEn": "Imagination",
  "types": [
   "Crafting"
  ],
  "category": "Dungeons I"
 },
 {
  "nameEn": "Lost in the Clouds",
  "types": [
   "Crafting"
  ],
  "category": "Locales I"
 },
 {
  "nameEn": "Painted Foothills",
  "types": [
   "Crafting"
  ],
  "category": "Locales I"
 },
 {
  "nameEn": "Solid",
  "types": [
   "Purchase"
  ],
  "category": "Locales I"
 },
 {
  "nameEn": "Contention",
  "types": [
   "Purchase"
  ],
  "category": "Quests"
 },
 {
  "nameEn": "Riptide",
  "types": [
   "Crafting",
   "Deep Dungeon"
  ],
  "category": "Dungeons I"
 },
 {
  "nameEn": "A Cold Wind",
  "types": [
   "Gold Saucer"
  ],
  "category": "Quests"
 },
 {
  "nameEn": "Four-sided Circle",
  "types": [
   "Gold Saucer"
  ],
  "category": "Locales I"
 },
 {
  "nameEn": "Dark Vows",
  "types": [
   "Crafting",
   "Deep Dungeon"
  ],
  "category": "Dungeons I"
 },
 {
  "nameEn": "Another Round",
  "types": [
   "Crafting"
  ],
  "category": "Locales I"
 },
 {
  "nameEn": "The Waking Sands",
  "types": [
   "Purchase"
  ],
  "category": "Locales I"
 },
 {
  "nameEn": "Answers",
  "types": [
   "Crafting"
  ],
  "category": "Raids I"
 },
 {
  "nameEn": "Sport of Kings",
  "types": [
   "Gold Saucer"
  ],
  "category": "Others"
 },
 {
  "nameEn": "From the Ashes",
  "types": [
   "Crafting"
  ],
  "category": "Raids I"
 },
 {
  "nameEn": "The Scars of Battle",
  "types": [
   "Crafting",
   "Deep Dungeon"
  ],
  "category": "Dungeons I"
 },
 {
  "nameEn": "A World Apart",
  "types": [
   "Crafting"
  ],
  "category": "Quests"
 },
 {
  "nameEn": "Rise of the White Raven",
  "types": [
   "Crafting"
  ],
  "category": "Raids I"
 },
 {
  "nameEn": "The Dark's Embrace",
  "types": [
   "Crafting"
  ],
  "category": "Dungeons I"
 },
 {
  "nameEn": "The Only Path",
  "types": [
   "Crafting"
  ],
  "category": "Quests"
 },
 {
  "nameEn": "A Light in the Storm",
  "types": [
   "Crafting",
   "Deep Dungeon"
  ],
  "category": "Dungeons I"
 },
 {
  "nameEn": "Thunderer",
  "types": [
   "Crafting"
  ],
  "category": "Raids I"
 },
 {
  "nameEn": "Agent of Inquiry",
  "types": [
   "Gold Saucer"
  ],
  "category": "Quests"
 },
 {
  "nameEn": "Eternal Wind",
  "types": [
   "Crafting"
  ],
  "category": "Raids I"
 },
 {
  "nameEn": "Fiend",
  "types": [
   "Crafting"
  ],
  "category": "Trials"
 },
 {
  "nameEn": "Hunger",
  "types": [
   "Crafting"
  ],
  "category": "Raids I"
 },
 {
  "nameEn": "Heroes",
  "types": [
   "Crafting"
  ],
  "category": "Trials"
 },
 {
  "nameEn": "Blind to the Dark",
  "types": [
   "Crafting"
  ],
  "category": "Raids I"
 },
 {
  "nameEn": "Under the Weight",
  "types": [
   "Crafting"
  ],
  "category": "Trials"
 },
 {
  "nameEn": "Starved",
  "types": [
   "Crafting"
  ],
  "category": "Others"
 },
 {
  "nameEn": "Fallen Angel",
  "types": [
   "Crafting"
  ],
  "category": "Trials"
 },
 {
  "nameEn": "Blood for Blood",
  "types": [
   "Crafting"
  ],
  "category": "Others"
 },
 {
  "nameEn": "Out of the Labyrinth",
  "types": [
   "Crafting"
  ],
  "category": "Raids I"
 },
 {
  "nameEn": "Primal Judgment",
  "types": [
   "Crafting"
  ],
  "category": "Trials"
 },
 {
  "nameEn": "When a Tree Falls",
  "types": [
   "Other"
  ],
  "category": "Others"
 },
 {
  "nameEn": "Now I Know the Truth",
  "types": [
   "Crafting"
  ],
  "category": "Raids I"
 },
 {
  "nameEn": "The Maker's Ruin",
  "types": [
   "Crafting"
  ],
  "category": "Trials"
 },
 {
  "nameEn": "A New Hope",
  "types": [
   "Purchase"
  ],
  "category": "Locales I"
 },
 {
  "nameEn": "Tumbling Down",
  "types": [
   "Crafting"
  ],
  "category": "Raids I"
 },
 {
  "nameEn": "Ultima",
  "types": [
   "Achievement"
  ],
  "category": "Trials"
 },
 {
  "nameEn": "Tenacity",
  "types": [
   "Other"
  ],
  "category": "Others"
 },
 {
  "nameEn": "I Am the Sea",
  "types": [
   "Purchase"
  ],
  "category": "Locales I"
 },
 {
  "nameEn": "Hubris",
  "types": [
   "Crafting"
  ],
  "category": "Raids I"
 },
 {
  "nameEn": "Torn from the Heavens",
  "types": [
   "Gold Saucer"
  ],
  "category": "Trials"
 },
 {
  "nameEn": "Prelude – Discoveries",
  "types": [
   "Achievement"
  ],
  "category": "Quests"
 },
 {
  "nameEn": "Wailers and Waterwheels",
  "types": [
   "Purchase"
  ],
  "category": "Locales I"
 },
 {
  "nameEn": "Pa-Paya",
  "types": [
   "Event",
   "Premium"
  ],
  "category": "Seasonal"
 }
]
